Workbook
Name cfg_Currency: Settings!$D$5
Name cfg_DefaultContribution: Settings!$D$6
Name cfg_FinancialYear: Settings!$D$7
Name cfg_StartMonth: Settings!$D$8
Name cfg_MaxMembers: Settings!$D$9
Name cfg_Theme: Settings!$D$10

Sheet Dashboard
A1: BOARDING HOUSE UTILITY MANAGEMENT SYSTEM - FINANCIAL DASHBOARD
A2: Visual overview of collections, utility expenditures, active roommates, net savings, and cash flows
B4: CURRENT MONTH | D4: TOTAL MEMBERS | F4: PAID MEMBERS | H4: UNPAID MEMBERS | J4: EXPECTED COLLECTION | L4: COLLECTED AMOUNT | N4: COLLECTION RATE % | P4: Status | Q4: Count
B5: =TEXT(TODAY(), "MMMM YYYY") | D5: =COUNTIF(tbl_Members[Status], "Active")+COUNTIF(tbl_Members[Status], "Inactive") | F5: =COUNTIF(tbl_Collections[Status], "Paid")+COUNTIF(tbl_Collections[Status], "Late") | H5: =COUNTIF(tbl_Collections[Status], "Not Paid") | J5: =SUM(tbl_MonthlySummary[Expected Collection]) | L5: =SUM(tbl_MonthlySummary[Actual Collection]) | N5: =IF(J5=0, 0, L5/J5) | P5: Paid | Q5: =COUNTIF(tbl_Collections[Status], "Paid")
P6: Partial | Q6: =COUNTIF(tbl_Collections[Status], "Partial")
B7: OUTSTANDING AMOUNT | D7: WATER EXPENSES | F7: ELECTRICITY EXPENSES | H7: TOTAL EXPENSES | J7: CARRY FORWARD BALANCE | L7: NET SAVINGS BALANCE | P7: Not Paid | Q7: =COUNTIF(tbl_Collections[Status], "Not Paid")
B8: =SUM(tbl_Collections[Outstanding Balance]) | D8: =SUM(tbl_MonthlySummary[Water Bills]) | F8: =SUM(tbl_MonthlySummary[Electricity Bills]) | H8: =SUM(tbl_MonthlySummary[Total Expenses]) | J8: =Monthly_Summary!$J$16 | L8: =L5-H8 | P8: Late | Q8: =COUNTIF(tbl_Collections[Status], "Late")
B10: FINANCIAL TRENDS & ANALYTICS OVERVIEW

Sheet Members
A1: BOARDING HOUSE MEMBERS DIRECTORY
A2: Manage active roommate profiles, room allocations, phone numbers and contract terms
A4: Member ID | B4: Full Name | C4: Room Number | D4: Phone Number | E4: Status | F4: Join Date | G4: Leave Date | H4: Notes
A5: ="MBR" & TEXT(ROW() - 4, "000")
A6: ="MBR" & TEXT(ROW() - 4, "000")
A7: ="MBR" & TEXT(ROW() - 4, "000")
A8: ="MBR" & TEXT(ROW() - 4, "000")
A9: ="MBR" & TEXT(ROW() - 4, "000")
A10: ="MBR" & TEXT(ROW() - 4, "000")
A11: ="MBR" & TEXT(ROW() - 4, "000")
A12: ="MBR" & TEXT(ROW() - 4, "000")
A13: ="MBR" & TEXT(ROW() - 4, "000")
A14: ="MBR" & TEXT(ROW() - 4, "000")
A15: ="MBR" & TEXT(ROW() - 4, "000")

Sheet Monthly_Collections
A1: MONTHLY ROOM RENT & UTILITY COLLECTIONS
A2: Record payments, split utilities, track collections and manage roommate balance accounts
B4: TOTAL RENT COLLECTED | E4: TOTAL OUTSTANDING DUE | H4: COLLECTION RATE
B5: =SUM(tbl_Collections[Total Paid]) | E5: =SUM(tbl_Collections[Outstanding Balance]) | H5: =IF((SUM(tbl_Collections[Standard Contribution])+SUM(tbl_Collections[Extra Contribution]))=0,0,SUM(tbl_Collections[Total Paid])/(SUM(tbl_Collections[Standard Contribution])+SUM(tbl_Collections[Extra Contribution])))
A8: Month | B8: Member | C8: Standard Contribution | D8: Extra Contribution | E8: Advance Payment | F8: Partial Payment | G8: Total Paid | H8: Outstanding Balance | I8: Payment Date | J8: Payment Status | K8: Remarks
C9: =Settings!$D$6 | D9: 0 | E9: 0 | F9: 0 | G9: =[@[Partial Payment]]+[@[Advance Payment]]+[@[Extra Contribution]] | H9: =MAX(0, [@[Standard Contribution]]+[@[Extra Contribution]]-[@[Total Paid]]) | J9: =IF([@[Total Paid]]=0, "Not Paid", IF([@[Total Paid]]<([@[Standard Contribution]]+[@[Extra Contribution]]), "Partial", IF(AND([@[Payment Date]]<>"", DAY([@[Payment Date]])>10), "Late", "Paid")))
C10: =Settings!$D$6 | D10: 0 | E10: 0 | F10: 0 | G10: =[@[Partial Payment]]+[@[Advance Payment]]+[@[Extra Contribution]] | H10: =MAX(0, [@[Standard Contribution]]+[@[Extra Contribution]]-[@[Total Paid]]) | J10: =IF([@[Total Paid]]=0, "Not Paid", IF([@[Total Paid]]<([@[Standard Contribution]]+[@[Extra Contribution]]), "Partial", IF(AND([@[Payment Date]]<>"", DAY([@[Payment Date]])>10), "Late", "Paid")))
C11: =Settings!$D$6 | D11: 0 | E11: 0 | F11: 0 | G11: =[@[Partial Payment]]+[@[Advance Payment]]+[@[Extra Contribution]] | H11: =MAX(0, [@[Standard Contribution]]+[@[Extra Contribution]]-[@[Total Paid]]) | J11: =IF([@[Total Paid]]=0, "Not Paid", IF([@[Total Paid]]<([@[Standard Contribution]]+[@[Extra Contribution]]), "Partial", IF(AND([@[Payment Date]]<>"", DAY([@[Payment Date]])>10), "Late", "Paid")))
C12: =Settings!$D$6 | D12: 0 | E12: 0 | F12: 0 | G12: =[@[Partial Payment]]+[@[Advance Payment]]+[@[Extra Contribution]] | H12: =MAX(0, [@[Standard Contribution]]+[@[Extra Contribution]]-[@[Total Paid]]) | J12: =IF([@[Total Paid]]=0, "Not Paid", IF([@[Total Paid]]<([@[Standard Contribution]]+[@[Extra Contribution]]), "Partial", IF(AND([@[Payment Date]]<>"", DAY([@[Payment Date]])>10), "Late", "Paid")))
C13: =Settings!$D$6 | D13: 0 | E13: 0 | F13: 0 | G13: =[@[Partial Payment]]+[@[Advance Payment]]+[@[Extra Contribution]] | H13: =MAX(0, [@[Standard Contribution]]+[@[Extra Contribution]]-[@[Total Paid]]) | J13: =IF([@[Total Paid]]=0, "Not Paid", IF([@[Total Paid]]<([@[Standard Contribution]]+[@[Extra Contribution]]), "Partial", IF(AND([@[Payment Date]]<>"", DAY([@[Payment Date]])>10), "Late", "Paid")))
C14: =Settings!$D$6 | D14: 0 | E14: 0 | F14: 0 | G14: =[@[Partial Payment]]+[@[Advance Payment]]+[@[Extra Contribution]] | H14: =MAX(0, [@[Standard Contribution]]+[@[Extra Contribution]]-[@[Total Paid]]) | J14: =IF([@[Total Paid]]=0, "Not Paid", IF([@[Total Paid]]<([@[Standard Contribution]]+[@[Extra Contribution]]), "Partial", IF(AND([@[Payment Date]]<>"", DAY([@[Payment Date]])>10), "Late", "Paid")))
C15: =Settings!$D$6 | D15: 0 | E15: 0 | F15: 0 | G15: =[@[Partial Payment]]+[@[Advance Payment]]+[@[Extra Contribution]] | H15: =MAX(0, [@[Standard Contribution]]+[@[Extra Contribution]]-[@[Total Paid]]) | J15: =IF([@[Total Paid]]=0, "Not Paid", IF([@[Total Paid]]<([@[Standard Contribution]]+[@[Extra Contribution]]), "Partial", IF(AND([@[Payment Date]]<>"", DAY([@[Payment Date]])>10), "Late", "Paid")))
C16: =Settings!$D$6 | D16: 0 | E16: 0 | F16: 0 | G16: =[@[Partial Payment]]+[@[Advance Payment]]+[@[Extra Contribution]] | H16: =MAX(0, [@[Standard Contribution]]+[@[Extra Contribution]]-[@[Total Paid]]) | J16: =IF([@[Total Paid]]=0, "Not Paid", IF([@[Total Paid]]<([@[Standard Contribution]]+[@[Extra Contribution]]), "Partial", IF(AND([@[Payment Date]]<>"", DAY([@[Payment Date]])>10), "Late", "Paid")))
C17: =Settings!$D$6 | D17: 0 | E17: 0 | F17: 0 | G17: =[@[Partial Payment]]+[@[Advance Payment]]+[@[Extra Contribution]] | H17: =MAX(0, [@[Standard Contribution]]+[@[Extra Contribution]]-[@[Total Paid]]) | J17: =IF([@[Total Paid]]=0, "Not Paid", IF([@[Total Paid]]<([@[Standard Contribution]]+[@[Extra Contribution]]), "Partial", IF(AND([@[Payment Date]]<>"", DAY([@[Payment Date]])>10), "Late", "Paid")))
C18: =Settings!$D$6 | D18: 0 | E18: 0 | F18: 0 | G18: =[@[Partial Payment]]+[@[Advance Payment]]+[@[Extra Contribution]] | H18: =MAX(0, [@[Standard Contribution]]+[@[Extra Contribution]]-[@[Total Paid]]) | J18: =IF([@[Total Paid]]=0, "Not Paid", IF([@[Total Paid]]<([@[Standard Contribution]]+[@[Extra Contribution]]), "Partial", IF(AND([@[Payment Date]]<>"", DAY([@[Payment Date]])>10), "Late", "Paid")))
C19: =Settings!$D$6 | D19: 0 | E19: 0 | F19: 0 | G19: =[@[Partial Payment]]+[@[Advance Payment]]+[@[Extra Contribution]] | H19: =MAX(0, [@[Standard Contribution]]+[@[Extra Contribution]]-[@[Total Paid]]) | J19: =IF([@[Total Paid]]=0, "Not Paid", IF([@[Total Paid]]<([@[Standard Contribution]]+[@[Extra Contribution]]), "Partial", IF(AND([@[Payment Date]]<>"", DAY([@[Payment Date]])>10), "Late", "Paid")))

Sheet Utility_Bills
A1: UTILITY BILLS MASTER LOG
A2: Track Water, Electricity, Internet, Gas, Cleaning, and other boarding operational expenditures
A4: Month | B4: Water Bill | C4: Electricity Bill | D4: Internet | E4: Gas | F4: Cleaning | G4: Other Expenses | H4: Total Expenses | I4: Bill Paid Date | J4: Paid By | K4: Remarks
B5: 0 | C5: 0 | D5: 0 | E5: 0 | F5: 0 | G5: 0 | H5: =[@[Water Bill]]+[@[Electricity Bill]]+[@[Internet]]+[@[Gas]]+[@[Cleaning]]+[@[Other Expenses]]
B6: 0 | C6: 0 | D6: 0 | E6: 0 | F6: 0 | G6: 0 | H6: =[@[Water Bill]]+[@[Electricity Bill]]+[@[Internet]]+[@[Gas]]+[@[Cleaning]]+[@[Other Expenses]]
B7: 0 | C7: 0 | D7: 0 | E7: 0 | F7: 0 | G7: 0 | H7: =[@[Water Bill]]+[@[Electricity Bill]]+[@[Internet]]+[@[Gas]]+[@[Cleaning]]+[@[Other Expenses]]
B8: 0 | C8: 0 | D8: 0 | E8: 0 | F8: 0 | G8: 0 | H8: =[@[Water Bill]]+[@[Electricity Bill]]+[@[Internet]]+[@[Gas]]+[@[Cleaning]]+[@[Other Expenses]]
B9: 0 | C9: 0 | D9: 0 | E9: 0 | F9: 0 | G9: 0 | H9: =[@[Water Bill]]+[@[Electricity Bill]]+[@[Internet]]+[@[Gas]]+[@[Cleaning]]+[@[Other Expenses]]
B10: 0 | C10: 0 | D10: 0 | E10: 0 | F10: 0 | G10: 0 | H10: =[@[Water Bill]]+[@[Electricity Bill]]+[@[Internet]]+[@[Gas]]+[@[Cleaning]]+[@[Other Expenses]]
B11: 0 | C11: 0 | D11: 0 | E11: 0 | F11: 0 | G11: 0 | H11: =[@[Water Bill]]+[@[Electricity Bill]]+[@[Internet]]+[@[Gas]]+[@[Cleaning]]+[@[Other Expenses]]
B12: 0 | C12: 0 | D12: 0 | E12: 0 | F12: 0 | G12: 0 | H12: =[@[Water Bill]]+[@[Electricity Bill]]+[@[Internet]]+[@[Gas]]+[@[Cleaning]]+[@[Other Expenses]]
B13: 0 | C13: 0 | D13: 0 | E13: 0 | F13: 0 | G13: 0 | H13: =[@[Water Bill]]+[@[Electricity Bill]]+[@[Internet]]+[@[Gas]]+[@[Cleaning]]+[@[Other Expenses]]
B14: 0 | C14: 0 | D14: 0 | E14: 0 | F14: 0 | G14: 0 | H14: =[@[Water Bill]]+[@[Electricity Bill]]+[@[Internet]]+[@[Gas]]+[@[Cleaning]]+[@[Other Expenses]]
B15: 0 | C15: 0 | D15: 0 | E15: 0 | F15: 0 | G15: 0 | H15: =[@[Water Bill]]+[@[Electricity Bill]]+[@[Internet]]+[@[Gas]]+[@[Cleaning]]+[@[Other Expenses]]
B16: 0 | C16: 0 | D16: 0 | E16: 0 | F16: 0 | G16: 0 | H16: =[@[Water Bill]]+[@[Electricity Bill]]+[@[Internet]]+[@[Gas]]+[@[Cleaning]]+[@[Other Expenses]]

Sheet Monthly_Summary
A1: MONTHLY FINANCIAL PERFORMANCE SUMMARY
A2: Aggregated roommate collections, utility bills, other expenses, net cash flows, and carry-forward balances
A4: Month | B4: Expected Collection | C4: Actual Collection | D4: Water Bills | E4: Electricity Bills | F4: Other Expenses | G4: Total Expenses | H4: Surplus | I4: Deficit | J4: Carry Forward | K4: Remarks
B5: =COUNTIF(tbl_Members[Status], "Active") * Settings!$D$6 | C5: =SUMIFS(tbl_Collections[Total Paid], tbl_Collections[Month], [@[Month]]) | D5: =SUMIFS(tbl_UtilityBills[Water Bill], tbl_UtilityBills[Month], [@[Month]]) | E5: =SUMIFS(tbl_UtilityBills[Electricity Bill], tbl_UtilityBills[Month], [@[Month]]) | F5: =SUMIFS(tbl_UtilityBills[Internet], tbl_UtilityBills[Month], [@[Month]])+SUMIFS(tbl_UtilityBills[Gas], tbl_UtilityBills[Month], [@[Month]])+SUMIFS(tbl_UtilityBills[Cleaning], tbl_UtilityBills[Month], [@[Month]])+SUMIFS(tbl_UtilityBills[Other Expenses], tbl_UtilityBills[Month], [@[Month]]) | G5: =[@[Water Bills]]+[@[Electricity Bills]]+[@[Other Expenses]] | H5: =IF([@[Actual Collection]]>[@[Total Expenses]], [@[Actual Collection]]-[@[Total Expenses]], 0) | I5: =IF([@[Total Expenses]]>[@[Actual Collection]], [@[Total Expenses]]-[@[Actual Collection]], 0) | J5: =[@[Actual Collection]]-[@[Total Expenses]]
B6: =COUNTIF(tbl_Members[Status], "Active") * Settings!$D$6 | C6: =SUMIFS(tbl_Collections[Total Paid], tbl_Collections[Month], [@[Month]]) | D6: =SUMIFS(tbl_UtilityBills[Water Bill], tbl_UtilityBills[Month], [@[Month]]) | E6: =SUMIFS(tbl_UtilityBills[Electricity Bill], tbl_UtilityBills[Month], [@[Month]]) | F6: =SUMIFS(tbl_UtilityBills[Internet], tbl_UtilityBills[Month], [@[Month]])+SUMIFS(tbl_UtilityBills[Gas], tbl_UtilityBills[Month], [@[Month]])+SUMIFS(tbl_UtilityBills[Cleaning], tbl_UtilityBills[Month], [@[Month]])+SUMIFS(tbl_UtilityBills[Other Expenses], tbl_UtilityBills[Month], [@[Month]]) | G6: =[@[Water Bills]]+[@[Electricity Bills]]+[@[Other Expenses]] | H6: =IF([@[Actual Collection]]>[@[Total Expenses]], [@[Actual Collection]]-[@[Total Expenses]], 0) | I6: =IF([@[Total Expenses]]>[@[Actual Collection]], [@[Total Expenses]]-[@[Actual Collection]], 0) | J6: =J5+[@[Actual Collection]]-[@[Total Expenses]]
B7: =COUNTIF(tbl_Members[Status], "Active") * Settings!$D$6 | C7: =SUMIFS(tbl_Collections[Total Paid], tbl_Collections[Month], [@[Month]]) | D7: =SUMIFS(tbl_UtilityBills[Water Bill], tbl_UtilityBills[Month], [@[Month]]) | E7: =SUMIFS(tbl_UtilityBills[Electricity Bill], tbl_UtilityBills[Month], [@[Month]]) | F7: =SUMIFS(tbl_UtilityBills[Internet], tbl_UtilityBills[Month], [@[Month]])+SUMIFS(tbl_UtilityBills[Gas], tbl_UtilityBills[Month], [@[Month]])+SUMIFS(tbl_UtilityBills[Cleaning], tbl_UtilityBills[Month], [@[Month]])+SUMIFS(tbl_UtilityBills[Other Expenses], tbl_UtilityBills[Month], [@[Month]]) | G7: =[@[Water Bills]]+[@[Electricity Bills]]+[@[Other Expenses]] | H7: =IF([@[Actual Collection]]>[@[Total Expenses]], [@[Actual Collection]]-[@[Total Expenses]], 0) | I7: =IF([@[Total Expenses]]>[@[Actual Collection]], [@[Total Expenses]]-[@[Actual Collection]], 0) | J7: =J6+[@[Actual Collection]]-[@[Total Expenses]]
B8: =COUNTIF(tbl_Members[Status], "Active") * Settings!$D$6 | C8: =SUMIFS(tbl_Collections[Total Paid], tbl_Collections[Month], [@[Month]]) | D8: =SUMIFS(tbl_UtilityBills[Water Bill], tbl_UtilityBills[Month], [@[Month]]) | E8: =SUMIFS(tbl_UtilityBills[Electricity Bill], tbl_UtilityBills[Month], [@[Month]]) | F8: =SUMIFS(tbl_UtilityBills[Internet], tbl_UtilityBills[Month], [@[Month]])+SUMIFS(tbl_UtilityBills[Gas], tbl_UtilityBills[Month], [@[Month]])+SUMIFS(tbl_UtilityBills[Cleaning], tbl_UtilityBills[Month], [@[Month]])+SUMIFS(tbl_UtilityBills[Other Expenses], tbl_UtilityBills[Month], [@[Month]]) | G8: =[@[Water Bills]]+[@[Electricity Bills]]+[@[Other Expenses]] | H8: =IF([@[Actual Collection]]>[@[Total Expenses]], [@[Actual Collection]]-[@[Total Expenses]], 0) | I8: =IF([@[Total Expenses]]>[@[Actual Collection]], [@[Total Expenses]]-[@[Actual Collection]], 0) | J8: =J7+[@[Actual Collection]]-[@[Total Expenses]]
B9: =COUNTIF(tbl_Members[Status], "Active") * Settings!$D$6 | C9: =SUMIFS(tbl_Collections[Total Paid], tbl_Collections[Month], [@[Month]]) | D9: =SUMIFS(tbl_UtilityBills[Water Bill], tbl_UtilityBills[Month], [@[Month]]) | E9: =SUMIFS(tbl_UtilityBills[Electricity Bill], tbl_UtilityBills[Month], [@[Month]]) | F9: =SUMIFS(tbl_UtilityBills[Internet], tbl_UtilityBills[Month], [@[Month]])+SUMIFS(tbl_UtilityBills[Gas], tbl_UtilityBills[Month], [@[Month]])+SUMIFS(tbl_UtilityBills[Cleaning], tbl_UtilityBills[Month], [@[Month]])+SUMIFS(tbl_UtilityBills[Other Expenses], tbl_UtilityBills[Month], [@[Month]]) | G9: =[@[Water Bills]]+[@[Electricity Bills]]+[@[Other Expenses]] | H9: =IF([@[Actual Collection]]>[@[Total Expenses]], [@[Actual Collection]]-[@[Total Expenses]], 0) | I9: =IF([@[Total Expenses]]>[@[Actual Collection]], [@[Total Expenses]]-[@[Actual Collection]], 0) | J9: =J8+[@[Actual Collection]]-[@[Total Expenses]]
B10: =COUNTIF(tbl_Members[Status], "Active") * Settings!$D$6 | C10: =SUMIFS(tbl_Collections[Total Paid], tbl_Collections[Month], [@[Month]]) | D10: =SUMIFS(tbl_UtilityBills[Water Bill], tbl_UtilityBills[Month], [@[Month]]) | E10: =SUMIFS(tbl_UtilityBills[Electricity Bill], tbl_UtilityBills[Month], [@[Month]]) | F10: =SUMIFS(tbl_UtilityBills[Internet], tbl_UtilityBills[Month], [@[Month]])+SUMIFS(tbl_UtilityBills[Gas], tbl_UtilityBills[Month], [@[Month]])+SUMIFS(tbl_UtilityBills[Cleaning], tbl_UtilityBills[Month], [@[Month]])+SUMIFS(tbl_UtilityBills[Other Expenses], tbl_UtilityBills[Month], [@[Month]]) | G10: =[@[Water Bills]]+[@[Electricity Bills]]+[@[Other Expenses]] | H10: =IF([@[Actual Collection]]>[@[Total Expenses]], [@[Actual Collection]]-[@[Total Expenses]], 0) | I10: =IF([@[Total Expenses]]>[@[Actual Collection]], [@[Total Expenses]]-[@[Actual Collection]], 0) | J10: =J9+[@[Actual Collection]]-[@[Total Expenses]]
B11: =COUNTIF(tbl_Members[Status], "Active") * Settings!$D$6 | C11: =SUMIFS(tbl_Collections[Total Paid], tbl_Collections[Month], [@[Month]]) | D11: =SUMIFS(tbl_UtilityBills[Water Bill], tbl_UtilityBills[Month], [@[Month]]) | E11: =SUMIFS(tbl_UtilityBills[Electricity Bill], tbl_UtilityBills[Month], [@[Month]]) | F11: =SUMIFS(tbl_UtilityBills[Internet], tbl_UtilityBills[Month], [@[Month]])+SUMIFS(tbl_UtilityBills[Gas], tbl_UtilityBills[Month], [@[Month]])+SUMIFS(tbl_UtilityBills[Cleaning], tbl_UtilityBills[Month], [@[Month]])+SUMIFS(tbl_UtilityBills[Other Expenses], tbl_UtilityBills[Month], [@[Month]]) | G11: =[@[Water Bills]]+[@[Electricity Bills]]+[@[Other Expenses]] | H11: =IF([@[Actual Collection]]>[@[Total Expenses]], [@[Actual Collection]]-[@[Total Expenses]], 0) | I11: =IF([@[Total Expenses]]>[@[Actual Collection]], [@[Total Expenses]]-[@[Actual Collection]], 0) | J11: =J10+[@[Actual Collection]]-[@[Total Expenses]]
B12: =COUNTIF(tbl_Members[Status], "Active") * Settings!$D$6 | C12: =SUMIFS(tbl_Collections[Total Paid], tbl_Collections[Month], [@[Month]]) | D12: =SUMIFS(tbl_UtilityBills[Water Bill], tbl_UtilityBills[Month], [@[Month]]) | E12: =SUMIFS(tbl_UtilityBills[Electricity Bill], tbl_UtilityBills[Month], [@[Month]]) | F12: =SUMIFS(tbl_UtilityBills[Internet], tbl_UtilityBills[Month], [@[Month]])+SUMIFS(tbl_UtilityBills[Gas], tbl_UtilityBills[Month], [@[Month]])+SUMIFS(tbl_UtilityBills[Cleaning], tbl_UtilityBills[Month], [@[Month]])+SUMIFS(tbl_UtilityBills[Other Expenses], tbl_UtilityBills[Month], [@[Month]]) | G12: =[@[Water Bills]]+[@[Electricity Bills]]+[@[Other Expenses]] | H12: =IF([@[Actual Collection]]>[@[Total Expenses]], [@[Actual Collection]]-[@[Total Expenses]], 0) | I12: =IF([@[Total Expenses]]>[@[Actual Collection]], [@[Total Expenses]]-[@[Actual Collection]], 0) | J12: =J11+[@[Actual Collection]]-[@[Total Expenses]]
B13: =COUNTIF(tbl_Members[Status], "Active") * Settings!$D$6 | C13: =SUMIFS(tbl_Collections[Total Paid], tbl_Collections[Month], [@[Month]]) | D13: =SUMIFS(tbl_UtilityBills[Water Bill], tbl_UtilityBills[Month], [@[Month]]) | E13: =SUMIFS(tbl_UtilityBills[Electricity Bill], tbl_UtilityBills[Month], [@[Month]]) | F13: =SUMIFS(tbl_UtilityBills[Internet], tbl_UtilityBills[Month], [@[Month]])+SUMIFS(tbl_UtilityBills[Gas], tbl_UtilityBills[Month], [@[Month]])+SUMIFS(tbl_UtilityBills[Cleaning], tbl_UtilityBills[Month], [@[Month]])+SUMIFS(tbl_UtilityBills[Other Expenses], tbl_UtilityBills[Month], [@[Month]]) | G13: =[@[Water Bills]]+[@[Electricity Bills]]+[@[Other Expenses]] | H13: =IF([@[Actual Collection]]>[@[Total Expenses]], [@[Actual Collection]]-[@[Total Expenses]], 0) | I13: =IF([@[Total Expenses]]>[@[Actual Collection]], [@[Total Expenses]]-[@[Actual Collection]], 0) | J13: =J12+[@[Actual Collection]]-[@[Total Expenses]]
B14: =COUNTIF(tbl_Members[Status], "Active") * Settings!$D$6 | C14: =SUMIFS(tbl_Collections[Total Paid], tbl_Collections[Month], [@[Month]]) | D14: =SUMIFS(tbl_UtilityBills[Water Bill], tbl_UtilityBills[Month], [@[Month]]) | E14: =SUMIFS(tbl_UtilityBills[Electricity Bill], tbl_UtilityBills[Month], [@[Month]]) | F14: =SUMIFS(tbl_UtilityBills[Internet], tbl_UtilityBills[Month], [@[Month]])+SUMIFS(tbl_UtilityBills[Gas], tbl_UtilityBills[Month], [@[Month]])+SUMIFS(tbl_UtilityBills[Cleaning], tbl_UtilityBills[Month], [@[Month]])+SUMIFS(tbl_UtilityBills[Other Expenses], tbl_UtilityBills[Month], [@[Month]]) | G14: =[@[Water Bills]]+[@[Electricity Bills]]+[@[Other Expenses]] | H14: =IF([@[Actual Collection]]>[@[Total Expenses]], [@[Actual Collection]]-[@[Total Expenses]], 0) | I14: =IF([@[Total Expenses]]>[@[Actual Collection]], [@[Total Expenses]]-[@[Actual Collection]], 0) | J14: =J13+[@[Actual Collection]]-[@[Total Expenses]]
B15: =COUNTIF(tbl_Members[Status], "Active") * Settings!$D$6 | C15: =SUMIFS(tbl_Collections[Total Paid], tbl_Collections[Month], [@[Month]]) | D15: =SUMIFS(tbl_UtilityBills[Water Bill], tbl_UtilityBills[Month], [@[Month]]) | E15: =SUMIFS(tbl_UtilityBills[Electricity Bill], tbl_UtilityBills[Month], [@[Month]]) | F15: =SUMIFS(tbl_UtilityBills[Internet], tbl_UtilityBills[Month], [@[Month]])+SUMIFS(tbl_UtilityBills[Gas], tbl_UtilityBills[Month], [@[Month]])+SUMIFS(tbl_UtilityBills[Cleaning], tbl_UtilityBills[Month], [@[Month]])+SUMIFS(tbl_UtilityBills[Other Expenses], tbl_UtilityBills[Month], [@[Month]]) | G15: =[@[Water Bills]]+[@[Electricity Bills]]+[@[Other Expenses]] | H15: =IF([@[Actual Collection]]>[@[Total Expenses]], [@[Actual Collection]]-[@[Total Expenses]], 0) | I15: =IF([@[Total Expenses]]>[@[Actual Collection]], [@[Total Expenses]]-[@[Actual Collection]], 0) | J15: =J14+[@[Actual Collection]]-[@[Total Expenses]]
B16: =COUNTIF(tbl_Members[Status], "Active") * Settings!$D$6 | C16: =SUMIFS(tbl_Collections[Total Paid], tbl_Collections[Month], [@[Month]]) | D16: =SUMIFS(tbl_UtilityBills[Water Bill], tbl_UtilityBills[Month], [@[Month]]) | E16: =SUMIFS(tbl_UtilityBills[Electricity Bill], tbl_UtilityBills[Month], [@[Month]]) | F16: =SUMIFS(tbl_UtilityBills[Internet], tbl_UtilityBills[Month], [@[Month]])+SUMIFS(tbl_UtilityBills[Gas], tbl_UtilityBills[Month], [@[Month]])+SUMIFS(tbl_UtilityBills[Cleaning], tbl_UtilityBills[Month], [@[Month]])+SUMIFS(tbl_UtilityBills[Other Expenses], tbl_UtilityBills[Month], [@[Month]]) | G16: =[@[Water Bills]]+[@[Electricity Bills]]+[@[Other Expenses]] | H16: =IF([@[Actual Collection]]>[@[Total Expenses]], [@[Actual Collection]]-[@[Total Expenses]], 0) | I16: =IF([@[Total Expenses]]>[@[Actual Collection]], [@[Total Expenses]]-[@[Actual Collection]], 0) | J16: =J15+[@[Actual Collection]]-[@[Total Expenses]]

Sheet Payment_Tracker
A1: YEARLY ROOMMATE PAYMENT STATUS TRACKER
A2: Cross-tab visual matrix displaying roommate payment status (Paid, Partial, Not Paid, Late) by month
A4: Member Name | B4: April | C4: May | D4: June | E4: July | F4: August | G4: September | H4: October | I4: November | J4: December | K4: January | L4: February | M4: March
A5: =IFERROR(INDEX(tbl_Members[Full Name], ROW() - 4), "") | B5: =IF([@[Member Name]]="", "", IFERROR(INDEX(tbl_Collections[Status], MATCH(1, INDEX((tbl_Collections[Member]=[@[Member Name]]) * (tbl_Collections[Month]=B$4), 0), 0)), "Not Paid")) | C5: =IF([@[Member Name]]="", "", IFERROR(INDEX(tbl_Collections[Status], MATCH(1, INDEX((tbl_Collections[Member]=[@[Member Name]]) * (tbl_Collections[Month]=C$4), 0), 0)), "Not Paid")) | D5: =IF([@[Member Name]]="", "", IFERROR(INDEX(tbl_Collections[Status], MATCH(1, INDEX((tbl_Collections[Member]=[@[Member Name]]) * (tbl_Collections[Month]=D$4), 0), 0)), "Not Paid")) | E5: =IF([@[Member Name]]="", "", IFERROR(INDEX(tbl_Collections[Status], MATCH(1, INDEX((tbl_Collections[Member]=[@[Member Name]]) * (tbl_Collections[Month]=E$4), 0), 0)), "Not Paid")) | F5: =IF([@[Member Name]]="", "", IFERROR(INDEX(tbl_Collections[Status], MATCH(1, INDEX((tbl_Collections[Member]=[@[Member Name]]) * (tbl_Collections[Month]=F$4), 0), 0)), "Not Paid")) | G5: =IF([@[Member Name]]="", "", IFERROR(INDEX(tbl_Collections[Status], MATCH(1, INDEX((tbl_Collections[Member]=[@[Member Name]]) * (tbl_Collections[Month]=G$4), 0), 0)), "Not Paid")) | H5: =IF([@[Member Name]]="", "", IFERROR(INDEX(tbl_Collections[Status], MATCH(1, INDEX((tbl_Collections[Member]=[@[Member Name]]) * (tbl_Collections[Month]=H$4), 0), 0)), "Not Paid")) | I5: =IF([@[Member Name]]="", "", IFERROR(INDEX(tbl_Collections[Status], MATCH(1, INDEX((tbl_Collections[Member]=[@[Member Name]]) * (tbl_Collections[Month]=I$4), 0), 0)), "Not Paid")) | ... M5: =IF([@[Member Name]]="", "", IFERROR(INDEX(tbl_Collections[Status], MATCH(1, INDEX((tbl_Collections[Member]=[@[Member Name]]) * (tbl_Collections[Month]=M$4), 0), 0)), "Not Paid"))
A6: =IFERROR(INDEX(tbl_Members[Full Name], ROW() - 4), "") | B6: =IF([@[Member Name]]="", "", IFERROR(INDEX(tbl_Collections[Status], MATCH(1, INDEX((tbl_Collections[Member]=[@[Member Name]]) * (tbl_Collections[Month]=B$4), 0), 0)), "Not Paid")) | C6: =IF([@[Member Name]]="", "", IFERROR(INDEX(tbl_Collections[Status], MATCH(1, INDEX((tbl_Collections[Member]=[@[Member Name]]) * (tbl_Collections[Month]=C$4), 0), 0)), "Not Paid")) | D6: =IF([@[Member Name]]="", "", IFERROR(INDEX(tbl_Collections[Status], MATCH(1, INDEX((tbl_Collections[Member]=[@[Member Name]]) * (tbl_Collections[Month]=D$4), 0), 0)), "Not Paid")) | E6: =IF([@[Member Name]]="", "", IFERROR(INDEX(tbl_Collections[Status], MATCH(1, INDEX((tbl_Collections[Member]=[@[Member Name]]) * (tbl_Collections[Month]=E$4), 0), 0)), "Not Paid")) | F6: =IF([@[Member Name]]="", "", IFERROR(INDEX(tbl_Collections[Status], MATCH(1, INDEX((tbl_Collections[Member]=[@[Member Name]]) * (tbl_Collections[Month]=F$4), 0), 0)), "Not Paid")) | G6: =IF([@[Member Name]]="", "", IFERROR(INDEX(tbl_Collections[Status], MATCH(1, INDEX((tbl_Collections[Member]=[@[Member Name]]) * (tbl_Collections[Month]=G$4), 0), 0)), "Not Paid")) | H6: =IF([@[Member Name]]="", "", IFERROR(INDEX(tbl_Collections[Status], MATCH(1, INDEX((tbl_Collections[Member]=[@[Member Name]]) * (tbl_Collections[Month]=H$4), 0), 0)), "Not Paid")) | I6: =IF([@[Member Name]]="", "", IFERROR(INDEX(tbl_Collections[Status], MATCH(1, INDEX((tbl_Collections[Member]=[@[Member Name]]) * (tbl_Collections[Month]=I$4), 0), 0)), "Not Paid")) | ... M6: =IF([@[Member Name]]="", "", IFERROR(INDEX(tbl_Collections[Status], MATCH(1, INDEX((tbl_Collections[Member]=[@[Member Name]]) * (tbl_Collections[Month]=M$4), 0), 0)), "Not Paid"))
A7: =IFERROR(INDEX(tbl_Members[Full Name], ROW() - 4), "") | B7: =IF([@[Member Name]]="", "", IFERROR(INDEX(tbl_Collections[Status], MATCH(1, INDEX((tbl_Collections[Member]=[@[Member Name]]) * (tbl_Collections[Month]=B$4), 0), 0)), "Not Paid")) | C7: =IF([@[Member Name]]="", "", IFERROR(INDEX(tbl_Collections[Status], MATCH(1, INDEX((tbl_Collections[Member]=[@[Member Name]]) * (tbl_Collections[Month]=C$4), 0), 0)), "Not Paid")) | D7: =IF([@[Member Name]]="", "", IFERROR(INDEX(tbl_Collections[Status], MATCH(1, INDEX((tbl_Collections[Member]=[@[Member Name]]) * (tbl_Collections[Month]=D$4), 0), 0)), "Not Paid")) | E7: =IF([@[Member Name]]="", "", IFERROR(INDEX(tbl_Collections[Status], MATCH(1, INDEX((tbl_Collections[Member]=[@[Member Name]]) * (tbl_Collections[Month]=E$4), 0), 0)), "Not Paid")) | F7: =IF([@[Member Name]]="", "", IFERROR(INDEX(tbl_Collections[Status], MATCH(1, INDEX((tbl_Collections[Member]=[@[Member Name]]) * (tbl_Collections[Month]=F$4), 0), 0)), "Not Paid")) | G7: =IF([@[Member Name]]="", "", IFERROR(INDEX(tbl_Collections[Status], MATCH(1, INDEX((tbl_Collections[Member]=[@[Member Name]]) * (tbl_Collections[Month]=G$4), 0), 0)), "Not Paid")) | H7: =IF([@[Member Name]]="", "", IFERROR(INDEX(tbl_Collections[Status], MATCH(1, INDEX((tbl_Collections[Member]=[@[Member Name]]) * (tbl_Collections[Month]=H$4), 0), 0)), "Not Paid")) | I7: =IF([@[Member Name]]="", "", IFERROR(INDEX(tbl_Collections[Status], MATCH(1, INDEX((tbl_Collections[Member]=[@[Member Name]]) * (tbl_Collections[Month]=I$4), 0), 0)), "Not Paid")) | ... M7: =IF([@[Member Name]]="", "", IFERROR(INDEX(tbl_Collections[Status], MATCH(1, INDEX((tbl_Collections[Member]=[@[Member Name]]) * (tbl_Collections[Month]=M$4), 0), 0)), "Not Paid"))
A8: =IFERROR(INDEX(tbl_Members[Full Name], ROW() - 4), "") | B8: =IF([@[Member Name]]="", "", IFERROR(INDEX(tbl_Collections[Status], MATCH(1, INDEX((tbl_Collections[Member]=[@[Member Name]]) * (tbl_Collections[Month]=B$4), 0), 0)), "Not Paid")) | C8: =IF([@[Member Name]]="", "", IFERROR(INDEX(tbl_Collections[Status], MATCH(1, INDEX((tbl_Collections[Member]=[@[Member Name]]) * (tbl_Collections[Month]=C$4), 0), 0)), "Not Paid")) | D8: =IF([@[Member Name]]="", "", IFERROR(INDEX(tbl_Collections[Status], MATCH(1, INDEX((tbl_Collections[Member]=[@[Member Name]]) * (tbl_Collections[Month]=D$4), 0), 0)), "Not Paid")) | E8: =IF([@[Member Name]]="", "", IFERROR(INDEX(tbl_Collections[Status], MATCH(1, INDEX((tbl_Collections[Member]=[@[Member Name]]) * (tbl_Collections[Month]=E$4), 0), 0)), "Not Paid")) | F8: =IF([@[Member Name]]="", "", IFERROR(INDEX(tbl_Collections[Status], MATCH(1, INDEX((tbl_Collections[Member]=[@[Member Name]]) * (tbl_Collections[Month]=F$4), 0), 0)), "Not Paid")) | G8: =IF([@[Member Name]]="", "", IFERROR(INDEX(tbl_Collections[Status], MATCH(1, INDEX((tbl_Collections[Member]=[@[Member Name]]) * (tbl_Collections[Month]=G$4), 0), 0)), "Not Paid")) | H8: =IF([@[Member Name]]="", "", IFERROR(INDEX(tbl_Collections[Status], MATCH(1, INDEX((tbl_Collections[Member]=[@[Member Name]]) * (tbl_Collections[Month]=H$4), 0), 0)), "Not Paid")) | I8: =IF([@[Member Name]]="", "", IFERROR(INDEX(tbl_Collections[Status], MATCH(1, INDEX((tbl_Collections[Member]=[@[Member Name]]) * (tbl_Collections[Month]=I$4), 0), 0)), "Not Paid")) | ... M8: =IF([@[Member Name]]="", "", IFERROR(INDEX(tbl_Collections[Status], MATCH(1, INDEX((tbl_Collections[Member]=[@[Member Name]]) * (tbl_Collections[Month]=M$4), 0), 0)), "Not Paid"))
A9: =IFERROR(INDEX(tbl_Members[Full Name], ROW() - 4), "") | B9: =IF([@[Member Name]]="", "", IFERROR(INDEX(tbl_Collections[Status], MATCH(1, INDEX((tbl_Collections[Member]=[@[Member Name]]) * (tbl_Collections[Month]=B$4), 0), 0)), "Not Paid")) | C9: =IF([@[Member Name]]="", "", IFERROR(INDEX(tbl_Collections[Status], MATCH(1, INDEX((tbl_Collections[Member]=[@[Member Name]]) * (tbl_Collections[Month]=C$4), 0), 0)), "Not Paid")) | D9: =IF([@[Member Name]]="", "", IFERROR(INDEX(tbl_Collections[Status], MATCH(1, INDEX((tbl_Collections[Member]=[@[Member Name]]) * (tbl_Collections[Month]=D$4), 0), 0)), "Not Paid")) | E9: =IF([@[Member Name]]="", "", IFERROR(INDEX(tbl_Collections[Status], MATCH(1, INDEX((tbl_Collections[Member]=[@[Member Name]]) * (tbl_Collections[Month]=E$4), 0), 0)), "Not Paid")) | F9: =IF([@[Member Name]]="", "", IFERROR(INDEX(tbl_Collections[Status], MATCH(1, INDEX((tbl_Collections[Member]=[@[Member Name]]) * (tbl_Collections[Month]=F$4), 0), 0)), "Not Paid")) | G9: =IF([@[Member Name]]="", "", IFERROR(INDEX(tbl_Collections[Status], MATCH(1, INDEX((tbl_Collections[Member]=[@[Member Name]]) * (tbl_Collections[Month]=G$4), 0), 0)), "Not Paid")) | H9: =IF([@[Member Name]]="", "", IFERROR(INDEX(tbl_Collections[Status], MATCH(1, INDEX((tbl_Collections[Member]=[@[Member Name]]) * (tbl_Collections[Month]=H$4), 0), 0)), "Not Paid")) | I9: =IF([@[Member Name]]="", "", IFERROR(INDEX(tbl_Collections[Status], MATCH(1, INDEX((tbl_Collections[Member]=[@[Member Name]]) * (tbl_Collections[Month]=I$4), 0), 0)), "Not Paid")) | ... M9: =IF([@[Member Name]]="", "", IFERROR(INDEX(tbl_Collections[Status], MATCH(1, INDEX((tbl_Collections[Member]=[@[Member Name]]) * (tbl_Collections[Month]=M$4), 0), 0)), "Not Paid"))
A10: =IFERROR(INDEX(tbl_Members[Full Name], ROW() - 4), "") | B10: =IF([@[Member Name]]="", "", IFERROR(INDEX(tbl_Collections[Status], MATCH(1, INDEX((tbl_Collections[Member]=[@[Member Name]]) * (tbl_Collections[Month]=B$4), 0), 0)), "Not Paid")) | C10: =IF([@[Member Name]]="", "", IFERROR(INDEX(tbl_Collections[Status], MATCH(1, INDEX((tbl_Collections[Member]=[@[Member Name]]) * (tbl_Collections[Month]=C$4), 0), 0)), "Not Paid")) | D10: =IF([@[Member Name]]="", "", IFERROR(INDEX(tbl_Collections[Status], MATCH(1, INDEX((tbl_Collections[Member]=[@[Member Name]]) * (tbl_Collections[Month]=D$4), 0), 0)), "Not Paid")) | E10: =IF([@[Member Name]]="", "", IFERROR(INDEX(tbl_Collections[Status], MATCH(1, INDEX((tbl_Collections[Member]=[@[Member Name]]) * (tbl_Collections[Month]=E$4), 0), 0)), "Not Paid")) | F10: =IF([@[Member Name]]="", "", IFERROR(INDEX(tbl_Collections[Status], MATCH(1, INDEX((tbl_Collections[Member]=[@[Member Name]]) * (tbl_Collections[Month]=F$4), 0), 0)), "Not Paid")) | G10: =IF([@[Member Name]]="", "", IFERROR(INDEX(tbl_Collections[Status], MATCH(1, INDEX((tbl_Collections[Member]=[@[Member Name]]) * (tbl_Collections[Month]=G$4), 0), 0)), "Not Paid")) | H10: =IF([@[Member Name]]="", "", IFERROR(INDEX(tbl_Collections[Status], MATCH(1, INDEX((tbl_Collections[Member]=[@[Member Name]]) * (tbl_Collections[Month]=H$4), 0), 0)), "Not Paid")) | I10: =IF([@[Member Name]]="", "", IFERROR(INDEX(tbl_Collections[Status], MATCH(1, INDEX((tbl_Collections[Member]=[@[Member Name]]) * (tbl_Collections[Month]=I$4), 0), 0)), "Not Paid")) | ... M10: =IF([@[Member Name]]="", "", IFERROR(INDEX(tbl_Collections[Status], MATCH(1, INDEX((tbl_Collections[Member]=[@[Member Name]]) * (tbl_Collections[Month]=M$4), 0), 0)), "Not Paid"))
A11: =IFERROR(INDEX(tbl_Members[Full Name], ROW() - 4), "") | B11: =IF([@[Member Name]]="", "", IFERROR(INDEX(tbl_Collections[Status], MATCH(1, INDEX((tbl_Collections[Member]=[@[Member Name]]) * (tbl_Collections[Month]=B$4), 0), 0)), "Not Paid")) | C11: =IF([@[Member Name]]="", "", IFERROR(INDEX(tbl_Collections[Status], MATCH(1, INDEX((tbl_Collections[Member]=[@[Member Name]]) * (tbl_Collections[Month]=C$4), 0), 0)), "Not Paid")) | D11: =IF([@[Member Name]]="", "", IFERROR(INDEX(tbl_Collections[Status], MATCH(1, INDEX((tbl_Collections[Member]=[@[Member Name]]) * (tbl_Collections[Month]=D$4), 0), 0)), "Not Paid")) | E11: =IF([@[Member Name]]="", "", IFERROR(INDEX(tbl_Collections[Status], MATCH(1, INDEX((tbl_Collections[Member]=[@[Member Name]]) * (tbl_Collections[Month]=E$4), 0), 0)), "Not Paid")) | F11: =IF([@[Member Name]]="", "", IFERROR(INDEX(tbl_Collections[Status], MATCH(1, INDEX((tbl_Collections[Member]=[@[Member Name]]) * (tbl_Collections[Month]=F$4), 0), 0)), "Not Paid")) | G11: =IF([@[Member Name]]="", "", IFERROR(INDEX(tbl_Collections[Status], MATCH(1, INDEX((tbl_Collections[Member]=[@[Member Name]]) * (tbl_Collections[Month]=G$4), 0), 0)), "Not Paid")) | H11: =IF([@[Member Name]]="", "", IFERROR(INDEX(tbl_Collections[Status], MATCH(1, INDEX((tbl_Collections[Member]=[@[Member Name]]) * (tbl_Collections[Month]=H$4), 0), 0)), "Not Paid")) | I11: =IF([@[Member Name]]="", "", IFERROR(INDEX(tbl_Collections[Status], MATCH(1, INDEX((tbl_Collections[Member]=[@[Member Name]]) * (tbl_Collections[Month]=I$4), 0), 0)), "Not Paid")) | ... M11: =IF([@[Member Name]]="", "", IFERROR(INDEX(tbl_Collections[Status], MATCH(1, INDEX((tbl_Collections[Member]=[@[Member Name]]) * (tbl_Collections[Month]=M$4), 0), 0)), "Not Paid"))
A12: =IFERROR(INDEX(tbl_Members[Full Name], ROW() - 4), "") | B12: =IF([@[Member Name]]="", "", IFERROR(INDEX(tbl_Collections[Status], MATCH(1, INDEX((tbl_Collections[Member]=[@[Member Name]]) * (tbl_Collections[Month]=B$4), 0), 0)), "Not Paid")) | C12: =IF([@[Member Name]]="", "", IFERROR(INDEX(tbl_Collections[Status], MATCH(1, INDEX((tbl_Collections[Member]=[@[Member Name]]) * (tbl_Collections[Month]=C$4), 0), 0)), "Not Paid")) | D12: =IF([@[Member Name]]="", "", IFERROR(INDEX(tbl_Collections[Status], MATCH(1, INDEX((tbl_Collections[Member]=[@[Member Name]]) * (tbl_Collections[Month]=D$4), 0), 0)), "Not Paid")) | E12: =IF([@[Member Name]]="", "", IFERROR(INDEX(tbl_Collections[Status], MATCH(1, INDEX((tbl_Collections[Member]=[@[Member Name]]) * (tbl_Collections[Month]=E$4), 0), 0)), "Not Paid")) | F12: =IF([@[Member Name]]="", "", IFERROR(INDEX(tbl_Collections[Status], MATCH(1, INDEX((tbl_Collections[Member]=[@[Member Name]]) * (tbl_Collections[Month]=F$4), 0), 0)), "Not Paid")) | G12: =IF([@[Member Name]]="", "", IFERROR(INDEX(tbl_Collections[Status], MATCH(1, INDEX((tbl_Collections[Member]=[@[Member Name]]) * (tbl_Collections[Month]=G$4), 0), 0)), "Not Paid")) | H12: =IF([@[Member Name]]="", "", IFERROR(INDEX(tbl_Collections[Status], MATCH(1, INDEX((tbl_Collections[Member]=[@[Member Name]]) * (tbl_Collections[Month]=H$4), 0), 0)), "Not Paid")) | I12: =IF([@[Member Name]]="", "", IFERROR(INDEX(tbl_Collections[Status], MATCH(1, INDEX((tbl_Collections[Member]=[@[Member Name]]) * (tbl_Collections[Month]=I$4), 0), 0)), "Not Paid")) | ... M12: =IF([@[Member Name]]="", "", IFERROR(INDEX(tbl_Collections[Status], MATCH(1, INDEX((tbl_Collections[Member]=[@[Member Name]]) * (tbl_Collections[Month]=M$4), 0), 0)), "Not Paid"))
A13: =IFERROR(INDEX(tbl_Members[Full Name], ROW() - 4), "") | B13: =IF([@[Member Name]]="", "", IFERROR(INDEX(tbl_Collections[Status], MATCH(1, INDEX((tbl_Collections[Member]=[@[Member Name]]) * (tbl_Collections[Month]=B$4), 0), 0)), "Not Paid")) | C13: =IF([@[Member Name]]="", "", IFERROR(INDEX(tbl_Collections[Status], MATCH(1, INDEX((tbl_Collections[Member]=[@[Member Name]]) * (tbl_Collections[Month]=C$4), 0), 0)), "Not Paid")) | D13: =IF([@[Member Name]]="", "", IFERROR(INDEX(tbl_Collections[Status], MATCH(1, INDEX((tbl_Collections[Member]=[@[Member Name]]) * (tbl_Collections[Month]=D$4), 0), 0)), "Not Paid")) | E13: =IF([@[Member Name]]="", "", IFERROR(INDEX(tbl_Collections[Status], MATCH(1, INDEX((tbl_Collections[Member]=[@[Member Name]]) * (tbl_Collections[Month]=E$4), 0), 0)), "Not Paid")) | F13: =IF([@[Member Name]]="", "", IFERROR(INDEX(tbl_Collections[Status], MATCH(1, INDEX((tbl_Collections[Member]=[@[Member Name]]) * (tbl_Collections[Month]=F$4), 0), 0)), "Not Paid")) | G13: =IF([@[Member Name]]="", "", IFERROR(INDEX(tbl_Collections[Status], MATCH(1, INDEX((tbl_Collections[Member]=[@[Member Name]]) * (tbl_Collections[Month]=G$4), 0), 0)), "Not Paid")) | H13: =IF([@[Member Name]]="", "", IFERROR(INDEX(tbl_Collections[Status], MATCH(1, INDEX((tbl_Collections[Member]=[@[Member Name]]) * (tbl_Collections[Month]=H$4), 0), 0)), "Not Paid")) | I13: =IF([@[Member Name]]="", "", IFERROR(INDEX(tbl_Collections[Status], MATCH(1, INDEX((tbl_Collections[Member]=[@[Member Name]]) * (tbl_Collections[Month]=I$4), 0), 0)), "Not Paid")) | ... M13: =IF([@[Member Name]]="", "", IFERROR(INDEX(tbl_Collections[Status], MATCH(1, INDEX((tbl_Collections[Member]=[@[Member Name]]) * (tbl_Collections[Month]=M$4), 0), 0)), "Not Paid"))
A14: =IFERROR(INDEX(tbl_Members[Full Name], ROW() - 4), "") | B14: =IF([@[Member Name]]="", "", IFERROR(INDEX(tbl_Collections[Status], MATCH(1, INDEX((tbl_Collections[Member]=[@[Member Name]]) * (tbl_Collections[Month]=B$4), 0), 0)), "Not Paid")) | C14: =IF([@[Member Name]]="", "", IFERROR(INDEX(tbl_Collections[Status], MATCH(1, INDEX((tbl_Collections[Member]=[@[Member Name]]) * (tbl_Collections[Month]=C$4), 0), 0)), "Not Paid")) | D14: =IF([@[Member Name]]="", "", IFERROR(INDEX(tbl_Collections[Status], MATCH(1, INDEX((tbl_Collections[Member]=[@[Member Name]]) * (tbl_Collections[Month]=D$4), 0), 0)), "Not Paid")) | E14: =IF([@[Member Name]]="", "", IFERROR(INDEX(tbl_Collections[Status], MATCH(1, INDEX((tbl_Collections[Member]=[@[Member Name]]) * (tbl_Collections[Month]=E$4), 0), 0)), "Not Paid")) | F14: =IF([@[Member Name]]="", "", IFERROR(INDEX(tbl_Collections[Status], MATCH(1, INDEX((tbl_Collections[Member]=[@[Member Name]]) * (tbl_Collections[Month]=F$4), 0), 0)), "Not Paid")) | G14: =IF([@[Member Name]]="", "", IFERROR(INDEX(tbl_Collections[Status], MATCH(1, INDEX((tbl_Collections[Member]=[@[Member Name]]) * (tbl_Collections[Month]=G$4), 0), 0)), "Not Paid")) | H14: =IF([@[Member Name]]="", "", IFERROR(INDEX(tbl_Collections[Status], MATCH(1, INDEX((tbl_Collections[Member]=[@[Member Name]]) * (tbl_Collections[Month]=H$4), 0), 0)), "Not Paid")) | I14: =IF([@[Member Name]]="", "", IFERROR(INDEX(tbl_Collections[Status], MATCH(1, INDEX((tbl_Collections[Member]=[@[Member Name]]) * (tbl_Collections[Month]=I$4), 0), 0)), "Not Paid")) | ... M14: =IF([@[Member Name]]="", "", IFERROR(INDEX(tbl_Collections[Status], MATCH(1, INDEX((tbl_Collections[Member]=[@[Member Name]]) * (tbl_Collections[Month]=M$4), 0), 0)), "Not Paid"))
A15: =IFERROR(INDEX(tbl_Members[Full Name], ROW() - 4), "") | B15: =IF([@[Member Name]]="", "", IFERROR(INDEX(tbl_Collections[Status], MATCH(1, INDEX((tbl_Collections[Member]=[@[Member Name]]) * (tbl_Collections[Month]=B$4), 0), 0)), "Not Paid")) | C15: =IF([@[Member Name]]="", "", IFERROR(INDEX(tbl_Collections[Status], MATCH(1, INDEX((tbl_Collections[Member]=[@[Member Name]]) * (tbl_Collections[Month]=C$4), 0), 0)), "Not Paid")) | D15: =IF([@[Member Name]]="", "", IFERROR(INDEX(tbl_Collections[Status], MATCH(1, INDEX((tbl_Collections[Member]=[@[Member Name]]) * (tbl_Collections[Month]=D$4), 0), 0)), "Not Paid")) | E15: =IF([@[Member Name]]="", "", IFERROR(INDEX(tbl_Collections[Status], MATCH(1, INDEX((tbl_Collections[Member]=[@[Member Name]]) * (tbl_Collections[Month]=E$4), 0), 0)), "Not Paid")) | F15: =IF([@[Member Name]]="", "", IFERROR(INDEX(tbl_Collections[Status], MATCH(1, INDEX((tbl_Collections[Member]=[@[Member Name]]) * (tbl_Collections[Month]=F$4), 0), 0)), "Not Paid")) | G15: =IF([@[Member Name]]="", "", IFERROR(INDEX(tbl_Collections[Status], MATCH(1, INDEX((tbl_Collections[Member]=[@[Member Name]]) * (tbl_Collections[Month]=G$4), 0), 0)), "Not Paid")) | H15: =IF([@[Member Name]]="", "", IFERROR(INDEX(tbl_Collections[Status], MATCH(1, INDEX((tbl_Collections[Member]=[@[Member Name]]) * (tbl_Collections[Month]=H$4), 0), 0)), "Not Paid")) | I15: =IF([@[Member Name]]="", "", IFERROR(INDEX(tbl_Collections[Status], MATCH(1, INDEX((tbl_Collections[Member]=[@[Member Name]]) * (tbl_Collections[Month]=I$4), 0), 0)), "Not Paid")) | ... M15: =IF([@[Member Name]]="", "", IFERROR(INDEX(tbl_Collections[Status], MATCH(1, INDEX((tbl_Collections[Member]=[@[Member Name]]) * (tbl_Collections[Month]=M$4), 0), 0)), "Not Paid"))
A16: =IFERROR(INDEX(tbl_Members[Full Name], ROW() - 4), "") | B16: =IF([@[Member Name]]="", "", IFERROR(INDEX(tbl_Collections[Status], MATCH(1, INDEX((tbl_Collections[Member]=[@[Member Name]]) * (tbl_Collections[Month]=B$4), 0), 0)), "Not Paid")) | C16: =IF([@[Member Name]]="", "", IFERROR(INDEX(tbl_Collections[Status], MATCH(1, INDEX((tbl_Collections[Member]=[@[Member Name]]) * (tbl_Collections[Month]=C$4), 0), 0)), "Not Paid")) | D16: =IF([@[Member Name]]="", "", IFERROR(INDEX(tbl_Collections[Status], MATCH(1, INDEX((tbl_Collections[Member]=[@[Member Name]]) * (tbl_Collections[Month]=D$4), 0), 0)), "Not Paid")) | E16: =IF([@[Member Name]]="", "", IFERROR(INDEX(tbl_Collections[Status], MATCH(1, INDEX((tbl_Collections[Member]=[@[Member Name]]) * (tbl_Collections[Month]=E$4), 0), 0)), "Not Paid")) | F16: =IF([@[Member Name]]="", "", IFERROR(INDEX(tbl_Collections[Status], MATCH(1, INDEX((tbl_Collections[Member]=[@[Member Name]]) * (tbl_Collections[Month]=F$4), 0), 0)), "Not Paid")) | G16: =IF([@[Member Name]]="", "", IFERROR(INDEX(tbl_Collections[Status], MATCH(1, INDEX((tbl_Collections[Member]=[@[Member Name]]) * (tbl_Collections[Month]=G$4), 0), 0)), "Not Paid")) | H16: =IF([@[Member Name]]="", "", IFERROR(INDEX(tbl_Collections[Status], MATCH(1, INDEX((tbl_Collections[Member]=[@[Member Name]]) * (tbl_Collections[Month]=H$4), 0), 0)), "Not Paid")) | I16: =IF([@[Member Name]]="", "", IFERROR(INDEX(tbl_Collections[Status], MATCH(1, INDEX((tbl_Collections[Member]=[@[Member Name]]) * (tbl_Collections[Month]=I$4), 0), 0)), "Not Paid")) | ... M16: =IF([@[Member Name]]="", "", IFERROR(INDEX(tbl_Collections[Status], MATCH(1, INDEX((tbl_Collections[Member]=[@[Member Name]]) * (tbl_Collections[Month]=M$4), 0), 0)), "Not Paid"))

Sheet Expense_History
A1: BOARDING HOUSE TRANSACTIONAL EXPENSE MASTER LOG
A2: Record miscellaneous boarding expenditures (left) and monitor aggregated monthly collections vs expenses (right)
A4: Expense ID | B4: Date | C4: Month | D4: Category | E4: Description | F4: Amount (LKR) | G4: Paid To | H4: Payment Method | I4: Reference No | K4: Year-Month | L4: Total Collections | M4: Total Expenses | N4: Difference | O4: Carry Forward
A5: ="EXP" & TEXT(ROW() - 4, "000") | C5: =IF([@Date]="", "", TEXT([@Date], "MMMM YYYY")) | F5: 0 | K5: April 2026 | L5: =SUMIFS(tbl_Collections[Total Paid], tbl_Collections[Month], [@[Year-Month]]) | M5: =SUMIFS(tbl_UtilityBills[Total Expenses], tbl_UtilityBills[Month], [@[Year-Month]])+SUMIFS(tbl_ExpenseHistory[Amount (LKR)], tbl_ExpenseHistory[Month], [@[Year-Month]]) | N5: =[@[Total Collections]]-[@[Total Expenses]] | O5: =[@[Difference]]
A6: ="EXP" & TEXT(ROW() - 4, "000") | C6: =IF([@Date]="", "", TEXT([@Date], "MMMM YYYY")) | F6: 0 | K6: May 2026 | L6: =SUMIFS(tbl_Collections[Total Paid], tbl_Collections[Month], [@[Year-Month]]) | M6: =SUMIFS(tbl_UtilityBills[Total Expenses], tbl_UtilityBills[Month], [@[Year-Month]])+SUMIFS(tbl_ExpenseHistory[Amount (LKR)], tbl_ExpenseHistory[Month], [@[Year-Month]]) | N6: =[@[Total Collections]]-[@[Total Expenses]] | O6: =O5+[@[Difference]]
A7: ="EXP" & TEXT(ROW() - 4, "000") | C7: =IF([@Date]="", "", TEXT([@Date], "MMMM YYYY")) | F7: 0 | K7: June 2026 | L7: =SUMIFS(tbl_Collections[Total Paid], tbl_Collections[Month], [@[Year-Month]]) | M7: =SUMIFS(tbl_UtilityBills[Total Expenses], tbl_UtilityBills[Month], [@[Year-Month]])+SUMIFS(tbl_ExpenseHistory[Amount (LKR)], tbl_ExpenseHistory[Month], [@[Year-Month]]) | N7: =[@[Total Collections]]-[@[Total Expenses]] | O7: =O6+[@[Difference]]
A8: ="EXP" & TEXT(ROW() - 4, "000") | C8: =IF([@Date]="", "", TEXT([@Date], "MMMM YYYY")) | F8: 0 | K8: July 2026 | L8: =SUMIFS(tbl_Collections[Total Paid], tbl_Collections[Month], [@[Year-Month]]) | M8: =SUMIFS(tbl_UtilityBills[Total Expenses], tbl_UtilityBills[Month], [@[Year-Month]])+SUMIFS(tbl_ExpenseHistory[Amount (LKR)], tbl_ExpenseHistory[Month], [@[Year-Month]]) | N8: =[@[Total Collections]]-[@[Total Expenses]] | O8: =O7+[@[Difference]]
A9: ="EXP" & TEXT(ROW() - 4, "000") | C9: =IF([@Date]="", "", TEXT([@Date], "MMMM YYYY")) | F9: 0 | K9: August 2026 | L9: =SUMIFS(tbl_Collections[Total Paid], tbl_Collections[Month], [@[Year-Month]]) | M9: =SUMIFS(tbl_UtilityBills[Total Expenses], tbl_UtilityBills[Month], [@[Year-Month]])+SUMIFS(tbl_ExpenseHistory[Amount (LKR)], tbl_ExpenseHistory[Month], [@[Year-Month]]) | N9: =[@[Total Collections]]-[@[Total Expenses]] | O9: =O8+[@[Difference]]
A10: ="EXP" & TEXT(ROW() - 4, "000") | C10: =IF([@Date]="", "", TEXT([@Date], "MMMM YYYY")) | F10: 0 | K10: September 2026 | L10: =SUMIFS(tbl_Collections[Total Paid], tbl_Collections[Month], [@[Year-Month]]) | M10: =SUMIFS(tbl_UtilityBills[Total Expenses], tbl_UtilityBills[Month], [@[Year-Month]])+SUMIFS(tbl_ExpenseHistory[Amount (LKR)], tbl_ExpenseHistory[Month], [@[Year-Month]]) | N10: =[@[Total Collections]]-[@[Total Expenses]] | O10: =O9+[@[Difference]]
A11: ="EXP" & TEXT(ROW() - 4, "000") | C11: =IF([@Date]="", "", TEXT([@Date], "MMMM YYYY")) | F11: 0 | K11: October 2026 | L11: =SUMIFS(tbl_Collections[Total Paid], tbl_Collections[Month], [@[Year-Month]]) | M11: =SUMIFS(tbl_UtilityBills[Total Expenses], tbl_UtilityBills[Month], [@[Year-Month]])+SUMIFS(tbl_ExpenseHistory[Amount (LKR)], tbl_ExpenseHistory[Month], [@[Year-Month]]) | N11: =[@[Total Collections]]-[@[Total Expenses]] | O11: =O10+[@[Difference]]
A12: ="EXP" & TEXT(ROW() - 4, "000") | C12: =IF([@Date]="", "", TEXT([@Date], "MMMM YYYY")) | F12: 0 | K12: November 2026 | L12: =SUMIFS(tbl_Collections[Total Paid], tbl_Collections[Month], [@[Year-Month]]) | M12: =SUMIFS(tbl_UtilityBills[Total Expenses], tbl_UtilityBills[Month], [@[Year-Month]])+SUMIFS(tbl_ExpenseHistory[Amount (LKR)], tbl_ExpenseHistory[Month], [@[Year-Month]]) | N12: =[@[Total Collections]]-[@[Total Expenses]] | O12: =O11+[@[Difference]]
A13: ="EXP" & TEXT(ROW() - 4, "000") | C13: =IF([@Date]="", "", TEXT([@Date], "MMMM YYYY")) | F13: 0 | K13: December 2026 | L13: =SUMIFS(tbl_Collections[Total Paid], tbl_Collections[Month], [@[Year-Month]]) | M13: =SUMIFS(tbl_UtilityBills[Total Expenses], tbl_UtilityBills[Month], [@[Year-Month]])+SUMIFS(tbl_ExpenseHistory[Amount (LKR)], tbl_ExpenseHistory[Month], [@[Year-Month]]) | N13: =[@[Total Collections]]-[@[Total Expenses]] | O13: =O12+[@[Difference]]
A14: ="EXP" & TEXT(ROW() - 4, "000") | C14: =IF([@Date]="", "", TEXT([@Date], "MMMM YYYY")) | F14: 0 | K14: January 2027 | L14: =SUMIFS(tbl_Collections[Total Paid], tbl_Collections[Month], [@[Year-Month]]) | M14: =SUMIFS(tbl_UtilityBills[Total Expenses], tbl_UtilityBills[Month], [@[Year-Month]])+SUMIFS(tbl_ExpenseHistory[Amount (LKR)], tbl_ExpenseHistory[Month], [@[Year-Month]]) | N14: =[@[Total Collections]]-[@[Total Expenses]] | O14: =O13+[@[Difference]]
A15: ="EXP" & TEXT(ROW() - 4, "000") | C15: =IF([@Date]="", "", TEXT([@Date], "MMMM YYYY")) | F15: 0 | K15: February 2027 | L15: =SUMIFS(tbl_Collections[Total Paid], tbl_Collections[Month], [@[Year-Month]]) | M15: =SUMIFS(tbl_UtilityBills[Total Expenses], tbl_UtilityBills[Month], [@[Year-Month]])+SUMIFS(tbl_ExpenseHistory[Amount (LKR)], tbl_ExpenseHistory[Month], [@[Year-Month]]) | N15: =[@[Total Collections]]-[@[Total Expenses]] | O15: =O14+[@[Difference]]
K16: March 2027 | L16: =SUMIFS(tbl_Collections[Total Paid], tbl_Collections[Month], [@[Year-Month]]) | M16: =SUMIFS(tbl_UtilityBills[Total Expenses], tbl_UtilityBills[Month], [@[Year-Month]])+SUMIFS(tbl_ExpenseHistory[Amount (LKR)], tbl_ExpenseHistory[Month], [@[Year-Month]]) | N16: =[@[Total Collections]]-[@[Total Expenses]] | O16: =O15+[@[Difference]]

Sheet Analytics
A1: BOARDING HOUSE SYSTEM METRICS & TREND ANALYTICS
A2: Overview of cost variance, collections distribution, highest utility expenditures and roommate payment ledgers
B4: HIGHEST UTILITY BILL | D4: LOWEST UTILITY BILL | F4: AVERAGE MONTHLY BILL | H4: AVERAGE COLLECTION | J4: TOTAL OUTSTANDING DUE | L4: MAX MONTHLY DEFICIT
B5: =MAX(tbl_UtilityBills[Total Expenses]) | D5: =IF(SUM(tbl_UtilityBills[Total Expenses])=0, 0, MINIFS(tbl_UtilityBills[Total Expenses], tbl_UtilityBills[Total Expenses], ">0")) | F5: =IFERROR(AVERAGE(tbl_UtilityBills[Total Expenses]), 0) | H5: =IFERROR(AVERAGE(tbl_Collections[Total Paid]), 0) | J5: =SUM(tbl_Collections[Outstanding Balance]) | L5: =MAX(tbl_MonthlySummary[Deficit])
B8: Member Name | C8: Total Rent Paid | D8: Total Utilities Paid | E8: Outstanding Balances
B9: =IFERROR(INDEX(tbl_Members[Full Name], ROW() - ROW(tbl_MemberAnalytics[[#Headers],[Member Name]])), "") | C9: =IF([@[Member Name]]="", "", SUMIFS(tbl_Collections[Partial Payment], tbl_Collections[Member], [@[Member Name]])) | D9: =IF([@[Member Name]]="", "", SUMIFS(tbl_Collections[Extra Contribution], tbl_Collections[Member], [@[Member Name]])) | E9: =IF([@[Member Name]]="", "", SUMIFS(tbl_Collections[Outstanding Balance], tbl_Collections[Member], [@[Member Name]]))
B10: =IFERROR(INDEX(tbl_Members[Full Name], ROW() - ROW(tbl_MemberAnalytics[[#Headers],[Member Name]])), "") | C10: =IF([@[Member Name]]="", "", SUMIFS(tbl_Collections[Partial Payment], tbl_Collections[Member], [@[Member Name]])) | D10: =IF([@[Member Name]]="", "", SUMIFS(tbl_Collections[Extra Contribution], tbl_Collections[Member], [@[Member Name]])) | E10: =IF([@[Member Name]]="", "", SUMIFS(tbl_Collections[Outstanding Balance], tbl_Collections[Member], [@[Member Name]]))
B11: =IFERROR(INDEX(tbl_Members[Full Name], ROW() - ROW(tbl_MemberAnalytics[[#Headers],[Member Name]])), "") | C11: =IF([@[Member Name]]="", "", SUMIFS(tbl_Collections[Partial Payment], tbl_Collections[Member], [@[Member Name]])) | D11: =IF([@[Member Name]]="", "", SUMIFS(tbl_Collections[Extra Contribution], tbl_Collections[Member], [@[Member Name]])) | E11: =IF([@[Member Name]]="", "", SUMIFS(tbl_Collections[Outstanding Balance], tbl_Collections[Member], [@[Member Name]]))
B12: =IFERROR(INDEX(tbl_Members[Full Name], ROW() - ROW(tbl_MemberAnalytics[[#Headers],[Member Name]])), "") | C12: =IF([@[Member Name]]="", "", SUMIFS(tbl_Collections[Partial Payment], tbl_Collections[Member], [@[Member Name]])) | D12: =IF([@[Member Name]]="", "", SUMIFS(tbl_Collections[Extra Contribution], tbl_Collections[Member], [@[Member Name]])) | E12: =IF([@[Member Name]]="", "", SUMIFS(tbl_Collections[Outstanding Balance], tbl_Collections[Member], [@[Member Name]]))
B13: =IFERROR(INDEX(tbl_Members[Full Name], ROW() - ROW(tbl_MemberAnalytics[[#Headers],[Member Name]])), "") | C13: =IF([@[Member Name]]="", "", SUMIFS(tbl_Collections[Partial Payment], tbl_Collections[Member], [@[Member Name]])) | D13: =IF([@[Member Name]]="", "", SUMIFS(tbl_Collections[Extra Contribution], tbl_Collections[Member], [@[Member Name]])) | E13: =IF([@[Member Name]]="", "", SUMIFS(tbl_Collections[Outstanding Balance], tbl_Collections[Member], [@[Member Name]]))
B14: =IFERROR(INDEX(tbl_Members[Full Name], ROW() - ROW(tbl_MemberAnalytics[[#Headers],[Member Name]])), "") | C14: =IF([@[Member Name]]="", "", SUMIFS(tbl_Collections[Partial Payment], tbl_Collections[Member], [@[Member Name]])) | D14: =IF([@[Member Name]]="", "", SUMIFS(tbl_Collections[Extra Contribution], tbl_Collections[Member], [@[Member Name]])) | E14: =IF([@[Member Name]]="", "", SUMIFS(tbl_Collections[Outstanding Balance], tbl_Collections[Member], [@[Member Name]]))
B15: =IFERROR(INDEX(tbl_Members[Full Name], ROW() - ROW(tbl_MemberAnalytics[[#Headers],[Member Name]])), "") | C15: =IF([@[Member Name]]="", "", SUMIFS(tbl_Collections[Partial Payment], tbl_Collections[Member], [@[Member Name]])) | D15: =IF([@[Member Name]]="", "", SUMIFS(tbl_Collections[Extra Contribution], tbl_Collections[Member], [@[Member Name]])) | E15: =IF([@[Member Name]]="", "", SUMIFS(tbl_Collections[Outstanding Balance], tbl_Collections[Member], [@[Member Name]]))
B16: =IFERROR(INDEX(tbl_Members[Full Name], ROW() - ROW(tbl_MemberAnalytics[[#Headers],[Member Name]])), "") | C16: =IF([@[Member Name]]="", "", SUMIFS(tbl_Collections[Partial Payment], tbl_Collections[Member], [@[Member Name]])) | D16: =IF([@[Member Name]]="", "", SUMIFS(tbl_Collections[Extra Contribution], tbl_Collections[Member], [@[Member Name]])) | E16: =IF([@[Member Name]]="", "", SUMIFS(tbl_Collections[Outstanding Balance], tbl_Collections[Member], [@[Member Name]]))
B17: =IFERROR(INDEX(tbl_Members[Full Name], ROW() - ROW(tbl_MemberAnalytics[[#Headers],[Member Name]])), "") | C17: =IF([@[Member Name]]="", "", SUMIFS(tbl_Collections[Partial Payment], tbl_Collections[Member], [@[Member Name]])) | D17: =IF([@[Member Name]]="", "", SUMIFS(tbl_Collections[Extra Contribution], tbl_Collections[Member], [@[Member Name]])) | E17: =IF([@[Member Name]]="", "", SUMIFS(tbl_Collections[Outstanding Balance], tbl_Collections[Member], [@[Member Name]]))
B18: =IFERROR(INDEX(tbl_Members[Full Name], ROW() - ROW(tbl_MemberAnalytics[[#Headers],[Member Name]])), "") | C18: =IF([@[Member Name]]="", "", SUMIFS(tbl_Collections[Partial Payment], tbl_Collections[Member], [@[Member Name]])) | D18: =IF([@[Member Name]]="", "", SUMIFS(tbl_Collections[Extra Contribution], tbl_Collections[Member], [@[Member Name]])) | E18: =IF([@[Member Name]]="", "", SUMIFS(tbl_Collections[Outstanding Balance], tbl_Collections[Member], [@[Member Name]]))
B19: =IFERROR(INDEX(tbl_Members[Full Name], ROW() - ROW(tbl_MemberAnalytics[[#Headers],[Member Name]])), "") | C19: =IF([@[Member Name]]="", "", SUMIFS(tbl_Collections[Partial Payment], tbl_Collections[Member], [@[Member Name]])) | D19: =IF([@[Member Name]]="", "", SUMIFS(tbl_Collections[Extra Contribution], tbl_Collections[Member], [@[Member Name]])) | E19: =IF([@[Member Name]]="", "", SUMIFS(tbl_Collections[Outstanding Balance], tbl_Collections[Member], [@[Member Name]]))

Sheet Reports
B1: BOARDING HOUSE UTILITY MANAGEMENT SYSTEM - REPORTS BINDER
B3: 1. MONTHLY COLLECTION SUMMARY REPORT
B4: Month | C4: Member Name | D4: Rent Due | E4: Utilities Due | F4: Total Paid | G4: Outstanding
B5: =IFERROR(INDEX(tbl_Collections[Month], ROW() - 4), "") | C5: =IFERROR(INDEX(tbl_Collections[Member], ROW() - 4), "") | D5: =IFERROR(INDEX(tbl_Collections[Standard Contribution], ROW() - 4), 0) | E5: =IFERROR(INDEX(tbl_Collections[Extra Contribution], ROW() - 4), 0) | F5: =IFERROR(INDEX(tbl_Collections[Total Paid], ROW() - 4), 0) | G5: =IFERROR(INDEX(tbl_Collections[Outstanding Balance], ROW() - 4), 0)
B6: =IFERROR(INDEX(tbl_Collections[Month], ROW() - 4), "") | C6: =IFERROR(INDEX(tbl_Collections[Member], ROW() - 4), "") | D6: =IFERROR(INDEX(tbl_Collections[Standard Contribution], ROW() - 4), 0) | E6: =IFERROR(INDEX(tbl_Collections[Extra Contribution], ROW() - 4), 0) | F6: =IFERROR(INDEX(tbl_Collections[Total Paid], ROW() - 4), 0) | G6: =IFERROR(INDEX(tbl_Collections[Outstanding Balance], ROW() - 4), 0)
B7: =IFERROR(INDEX(tbl_Collections[Month], ROW() - 4), "") | C7: =IFERROR(INDEX(tbl_Collections[Member], ROW() - 4), "") | D7: =IFERROR(INDEX(tbl_Collections[Standard Contribution], ROW() - 4), 0) | E7: =IFERROR(INDEX(tbl_Collections[Extra Contribution], ROW() - 4), 0) | F7: =IFERROR(INDEX(tbl_Collections[Total Paid], ROW() - 4), 0) | G7: =IFERROR(INDEX(tbl_Collections[Outstanding Balance], ROW() - 4), 0)
B8: =IFERROR(INDEX(tbl_Collections[Month], ROW() - 4), "") | C8: =IFERROR(INDEX(tbl_Collections[Member], ROW() - 4), "") | D8: =IFERROR(INDEX(tbl_Collections[Standard Contribution], ROW() - 4), 0) | E8: =IFERROR(INDEX(tbl_Collections[Extra Contribution], ROW() - 4), 0) | F8: =IFERROR(INDEX(tbl_Collections[Total Paid], ROW() - 4), 0) | G8: =IFERROR(INDEX(tbl_Collections[Outstanding Balance], ROW() - 4), 0)
B9: =IFERROR(INDEX(tbl_Collections[Month], ROW() - 4), "") | C9: =IFERROR(INDEX(tbl_Collections[Member], ROW() - 4), "") | D9: =IFERROR(INDEX(tbl_Collections[Standard Contribution], ROW() - 4), 0) | E9: =IFERROR(INDEX(tbl_Collections[Extra Contribution], ROW() - 4), 0) | F9: =IFERROR(INDEX(tbl_Collections[Total Paid], ROW() - 4), 0) | G9: =IFERROR(INDEX(tbl_Collections[Outstanding Balance], ROW() - 4), 0)
B10: =IFERROR(INDEX(tbl_Collections[Month], ROW() - 4), "") | C10: =IFERROR(INDEX(tbl_Collections[Member], ROW() - 4), "") | D10: =IFERROR(INDEX(tbl_Collections[Standard Contribution], ROW() - 4), 0) | E10: =IFERROR(INDEX(tbl_Collections[Extra Contribution], ROW() - 4), 0) | F10: =IFERROR(INDEX(tbl_Collections[Total Paid], ROW() - 4), 0) | G10: =IFERROR(INDEX(tbl_Collections[Outstanding Balance], ROW() - 4), 0)
B11: =IFERROR(INDEX(tbl_Collections[Month], ROW() - 4), "") | C11: =IFERROR(INDEX(tbl_Collections[Member], ROW() - 4), "") | D11: =IFERROR(INDEX(tbl_Collections[Standard Contribution], ROW() - 4), 0) | E11: =IFERROR(INDEX(tbl_Collections[Extra Contribution], ROW() - 4), 0) | F11: =IFERROR(INDEX(tbl_Collections[Total Paid], ROW() - 4), 0) | G11: =IFERROR(INDEX(tbl_Collections[Outstanding Balance], ROW() - 4), 0)
B12: =IFERROR(INDEX(tbl_Collections[Month], ROW() - 4), "") | C12: =IFERROR(INDEX(tbl_Collections[Member], ROW() - 4), "") | D12: =IFERROR(INDEX(tbl_Collections[Standard Contribution], ROW() - 4), 0) | E12: =IFERROR(INDEX(tbl_Collections[Extra Contribution], ROW() - 4), 0) | F12: =IFERROR(INDEX(tbl_Collections[Total Paid], ROW() - 4), 0) | G12: =IFERROR(INDEX(tbl_Collections[Outstanding Balance], ROW() - 4), 0)
B13: =IFERROR(INDEX(tbl_Collections[Month], ROW() - 4), "") | C13: =IFERROR(INDEX(tbl_Collections[Member], ROW() - 4), "") | D13: =IFERROR(INDEX(tbl_Collections[Standard Contribution], ROW() - 4), 0) | E13: =IFERROR(INDEX(tbl_Collections[Extra Contribution], ROW() - 4), 0) | F13: =IFERROR(INDEX(tbl_Collections[Total Paid], ROW() - 4), 0) | G13: =IFERROR(INDEX(tbl_Collections[Outstanding Balance], ROW() - 4), 0)
B14: =IFERROR(INDEX(tbl_Collections[Month], ROW() - 4), "") | C14: =IFERROR(INDEX(tbl_Collections[Member], ROW() - 4), "") | D14: =IFERROR(INDEX(tbl_Collections[Standard Contribution], ROW() - 4), 0) | E14: =IFERROR(INDEX(tbl_Collections[Extra Contribution], ROW() - 4), 0) | F14: =IFERROR(INDEX(tbl_Collections[Total Paid], ROW() - 4), 0) | G14: =IFERROR(INDEX(tbl_Collections[Outstanding Balance], ROW() - 4), 0)
B15: =IFERROR(INDEX(tbl_Collections[Month], ROW() - 4), "") | C15: =IFERROR(INDEX(tbl_Collections[Member], ROW() - 4), "") | D15: =IFERROR(INDEX(tbl_Collections[Standard Contribution], ROW() - 4), 0) | E15: =IFERROR(INDEX(tbl_Collections[Extra Contribution], ROW() - 4), 0) | F15: =IFERROR(INDEX(tbl_Collections[Total Paid], ROW() - 4), 0) | G15: =IFERROR(INDEX(tbl_Collections[Outstanding Balance], ROW() - 4), 0)
B16: =IFERROR(INDEX(tbl_Collections[Month], ROW() - 4), "") | C16: =IFERROR(INDEX(tbl_Collections[Member], ROW() - 4), "") | D16: =IFERROR(INDEX(tbl_Collections[Standard Contribution], ROW() - 4), 0) | E16: =IFERROR(INDEX(tbl_Collections[Extra Contribution], ROW() - 4), 0) | F16: =IFERROR(INDEX(tbl_Collections[Total Paid], ROW() - 4), 0) | G16: =IFERROR(INDEX(tbl_Collections[Outstanding Balance], ROW() - 4), 0)
B18: 2. MONTHLY EXPENSE BREAKDOWN REPORT
B19: Month | C19: Water Bill | D19: Electricity Bill | E19: Internet Share | F19: Cleaning & Gas | G19: Total Expenses
B20: =IFERROR(INDEX(tbl_UtilityBills[Month], ROW() - 19), "") | C20: =IFERROR(INDEX(tbl_UtilityBills[Water Bill], ROW() - 19), 0) | D20: =IFERROR(INDEX(tbl_UtilityBills[Electricity Bill], ROW() - 19), 0) | E20: =IFERROR(INDEX(tbl_UtilityBills[Internet], ROW() - 19), 0) | F20: =IFERROR(INDEX(tbl_UtilityBills[Cleaning], ROW() - 19)+INDEX(tbl_UtilityBills[Gas], ROW() - 19), 0) | G20: =IFERROR(INDEX(tbl_UtilityBills[Total Expenses], ROW() - 19), 0)
B21: =IFERROR(INDEX(tbl_UtilityBills[Month], ROW() - 19), "") | C21: =IFERROR(INDEX(tbl_UtilityBills[Water Bill], ROW() - 19), 0) | D21: =IFERROR(INDEX(tbl_UtilityBills[Electricity Bill], ROW() - 19), 0) | E21: =IFERROR(INDEX(tbl_UtilityBills[Internet], ROW() - 19), 0) | F21: =IFERROR(INDEX(tbl_UtilityBills[Cleaning], ROW() - 19)+INDEX(tbl_UtilityBills[Gas], ROW() - 19), 0) | G21: =IFERROR(INDEX(tbl_UtilityBills[Total Expenses], ROW() - 19), 0)
B22: =IFERROR(INDEX(tbl_UtilityBills[Month], ROW() - 19), "") | C22: =IFERROR(INDEX(tbl_UtilityBills[Water Bill], ROW() - 19), 0) | D22: =IFERROR(INDEX(tbl_UtilityBills[Electricity Bill], ROW() - 19), 0) | E22: =IFERROR(INDEX(tbl_UtilityBills[Internet], ROW() - 19), 0) | F22: =IFERROR(INDEX(tbl_UtilityBills[Cleaning], ROW() - 19)+INDEX(tbl_UtilityBills[Gas], ROW() - 19), 0) | G22: =IFERROR(INDEX(tbl_UtilityBills[Total Expenses], ROW() - 19), 0)
B23: =IFERROR(INDEX(tbl_UtilityBills[Month], ROW() - 19), "") | C23: =IFERROR(INDEX(tbl_UtilityBills[Water Bill], ROW() - 19), 0) | D23: =IFERROR(INDEX(tbl_UtilityBills[Electricity Bill], ROW() - 19), 0) | E23: =IFERROR(INDEX(tbl_UtilityBills[Internet], ROW() - 19), 0) | F23: =IFERROR(INDEX(tbl_UtilityBills[Cleaning], ROW() - 19)+INDEX(tbl_UtilityBills[Gas], ROW() - 19), 0) | G23: =IFERROR(INDEX(tbl_UtilityBills[Total Expenses], ROW() - 19), 0)
B24: =IFERROR(INDEX(tbl_UtilityBills[Month], ROW() - 19), "") | C24: =IFERROR(INDEX(tbl_UtilityBills[Water Bill], ROW() - 19), 0) | D24: =IFERROR(INDEX(tbl_UtilityBills[Electricity Bill], ROW() - 19), 0) | E24: =IFERROR(INDEX(tbl_UtilityBills[Internet], ROW() - 19), 0) | F24: =IFERROR(INDEX(tbl_UtilityBills[Cleaning], ROW() - 19)+INDEX(tbl_UtilityBills[Gas], ROW() - 19), 0) | G24: =IFERROR(INDEX(tbl_UtilityBills[Total Expenses], ROW() - 19), 0)
B25: =IFERROR(INDEX(tbl_UtilityBills[Month], ROW() - 19), "") | C25: =IFERROR(INDEX(tbl_UtilityBills[Water Bill], ROW() - 19), 0) | D25: =IFERROR(INDEX(tbl_UtilityBills[Electricity Bill], ROW() - 19), 0) | E25: =IFERROR(INDEX(tbl_UtilityBills[Internet], ROW() - 19), 0) | F25: =IFERROR(INDEX(tbl_UtilityBills[Cleaning], ROW() - 19)+INDEX(tbl_UtilityBills[Gas], ROW() - 19), 0) | G25: =IFERROR(INDEX(tbl_UtilityBills[Total Expenses], ROW() - 19), 0)
B26: =IFERROR(INDEX(tbl_UtilityBills[Month], ROW() - 19), "") | C26: =IFERROR(INDEX(tbl_UtilityBills[Water Bill], ROW() - 19), 0) | D26: =IFERROR(INDEX(tbl_UtilityBills[Electricity Bill], ROW() - 19), 0) | E26: =IFERROR(INDEX(tbl_UtilityBills[Internet], ROW() - 19), 0) | F26: =IFERROR(INDEX(tbl_UtilityBills[Cleaning], ROW() - 19)+INDEX(tbl_UtilityBills[Gas], ROW() - 19), 0) | G26: =IFERROR(INDEX(tbl_UtilityBills[Total Expenses], ROW() - 19), 0)
B27: =IFERROR(INDEX(tbl_UtilityBills[Month], ROW() - 19), "") | C27: =IFERROR(INDEX(tbl_UtilityBills[Water Bill], ROW() - 19), 0) | D27: =IFERROR(INDEX(tbl_UtilityBills[Electricity Bill], ROW() - 19), 0) | E27: =IFERROR(INDEX(tbl_UtilityBills[Internet], ROW() - 19), 0) | F27: =IFERROR(INDEX(tbl_UtilityBills[Cleaning], ROW() - 19)+INDEX(tbl_UtilityBills[Gas], ROW() - 19), 0) | G27: =IFERROR(INDEX(tbl_UtilityBills[Total Expenses], ROW() - 19), 0)
B28: =IFERROR(INDEX(tbl_UtilityBills[Month], ROW() - 19), "") | C28: =IFERROR(INDEX(tbl_UtilityBills[Water Bill], ROW() - 19), 0) | D28: =IFERROR(INDEX(tbl_UtilityBills[Electricity Bill], ROW() - 19), 0) | E28: =IFERROR(INDEX(tbl_UtilityBills[Internet], ROW() - 19), 0) | F28: =IFERROR(INDEX(tbl_UtilityBills[Cleaning], ROW() - 19)+INDEX(tbl_UtilityBills[Gas], ROW() - 19), 0) | G28: =IFERROR(INDEX(tbl_UtilityBills[Total Expenses], ROW() - 19), 0)
B29: =IFERROR(INDEX(tbl_UtilityBills[Month], ROW() - 19), "") | C29: =IFERROR(INDEX(tbl_UtilityBills[Water Bill], ROW() - 19), 0) | D29: =IFERROR(INDEX(tbl_UtilityBills[Electricity Bill], ROW() - 19), 0) | E29: =IFERROR(INDEX(tbl_UtilityBills[Internet], ROW() - 19), 0) | F29: =IFERROR(INDEX(tbl_UtilityBills[Cleaning], ROW() - 19)+INDEX(tbl_UtilityBills[Gas], ROW() - 19), 0) | G29: =IFERROR(INDEX(tbl_UtilityBills[Total Expenses], ROW() - 19), 0)
B30: =IFERROR(INDEX(tbl_UtilityBills[Month], ROW() - 19), "") | C30: =IFERROR(INDEX(tbl_UtilityBills[Water Bill], ROW() - 19), 0) | D30: =IFERROR(INDEX(tbl_UtilityBills[Electricity Bill], ROW() - 19), 0) | E30: =IFERROR(INDEX(tbl_UtilityBills[Internet], ROW() - 19), 0) | F30: =IFERROR(INDEX(tbl_UtilityBills[Cleaning], ROW() - 19)+INDEX(tbl_UtilityBills[Gas], ROW() - 19), 0) | G30: =IFERROR(INDEX(tbl_UtilityBills[Total Expenses], ROW() - 19), 0)
B31: =IFERROR(INDEX(tbl_UtilityBills[Month], ROW() - 19), "") | C31: =IFERROR(INDEX(tbl_UtilityBills[Water Bill], ROW() - 19), 0) | D31: =IFERROR(INDEX(tbl_UtilityBills[Electricity Bill], ROW() - 19), 0) | E31: =IFERROR(INDEX(tbl_UtilityBills[Internet], ROW() - 19), 0) | F31: =IFERROR(INDEX(tbl_UtilityBills[Cleaning], ROW() - 19)+INDEX(tbl_UtilityBills[Gas], ROW() - 19), 0) | G31: =IFERROR(INDEX(tbl_UtilityBills[Total Expenses], ROW() - 19), 0)
B33: 3. ROOMMATE OUTSTANDING BALANCES REPORT
B34: Month | C34: Member Name | D34: Expected Amount | E34: Total Paid | F34: Outstanding Balance | G34: Status
B35: =IFERROR(INDEX(tbl_Collections[Month], ROW() - 34), "") | C35: =IFERROR(INDEX(tbl_Collections[Member], ROW() - 34), "") | D35: =IFERROR(INDEX(tbl_Collections[Standard Contribution], ROW() - 34)+INDEX(tbl_Collections[Extra Contribution], ROW() - 34), 0) | E35: =IFERROR(INDEX(tbl_Collections[Total Paid], ROW() - 34), 0) | F35: =IFERROR(INDEX(tbl_Collections[Outstanding Balance], ROW() - 34), 0) | G35: =IFERROR(INDEX(tbl_Collections[Status], ROW() - 34), "")
B36: =IFERROR(INDEX(tbl_Collections[Month], ROW() - 34), "") | C36: =IFERROR(INDEX(tbl_Collections[Member], ROW() - 34), "") | D36: =IFERROR(INDEX(tbl_Collections[Standard Contribution], ROW() - 34)+INDEX(tbl_Collections[Extra Contribution], ROW() - 34), 0) | E36: =IFERROR(INDEX(tbl_Collections[Total Paid], ROW() - 34), 0) | F36: =IFERROR(INDEX(tbl_Collections[Outstanding Balance], ROW() - 34), 0) | G36: =IFERROR(INDEX(tbl_Collections[Status], ROW() - 34), "")
B37: =IFERROR(INDEX(tbl_Collections[Month], ROW() - 34), "") | C37: =IFERROR(INDEX(tbl_Collections[Member], ROW() - 34), "") | D37: =IFERROR(INDEX(tbl_Collections[Standard Contribution], ROW() - 34)+INDEX(tbl_Collections[Extra Contribution], ROW() - 34), 0) | E37: =IFERROR(INDEX(tbl_Collections[Total Paid], ROW() - 34), 0) | F37: =IFERROR(INDEX(tbl_Collections[Outstanding Balance], ROW() - 34), 0) | G37: =IFERROR(INDEX(tbl_Collections[Status], ROW() - 34), "")
B38: =IFERROR(INDEX(tbl_Collections[Month], ROW() - 34), "") | C38: =IFERROR(INDEX(tbl_Collections[Member], ROW() - 34), "") | D38: =IFERROR(INDEX(tbl_Collections[Standard Contribution], ROW() - 34)+INDEX(tbl_Collections[Extra Contribution], ROW() - 34), 0) | E38: =IFERROR(INDEX(tbl_Collections[Total Paid], ROW() - 34), 0) | F38: =IFERROR(INDEX(tbl_Collections[Outstanding Balance], ROW() - 34), 0) | G38: =IFERROR(INDEX(tbl_Collections[Status], ROW() - 34), "")
B39: =IFERROR(INDEX(tbl_Collections[Month], ROW() - 34), "") | C39: =IFERROR(INDEX(tbl_Collections[Member], ROW() - 34), "") | D39: =IFERROR(INDEX(tbl_Collections[Standard Contribution], ROW() - 34)+INDEX(tbl_Collections[Extra Contribution], ROW() - 34), 0) | E39: =IFERROR(INDEX(tbl_Collections[Total Paid], ROW() - 34), 0) | F39: =IFERROR(INDEX(tbl_Collections[Outstanding Balance], ROW() - 34), 0) | G39: =IFERROR(INDEX(tbl_Collections[Status], ROW() - 34), "")
B40: =IFERROR(INDEX(tbl_Collections[Month], ROW() - 34), "") | C40: =IFERROR(INDEX(tbl_Collections[Member], ROW() - 34), "") | D40: =IFERROR(INDEX(tbl_Collections[Standard Contribution], ROW() - 34)+INDEX(tbl_Collections[Extra Contribution], ROW() - 34), 0) | E40: =IFERROR(INDEX(tbl_Collections[Total Paid], ROW() - 34), 0) | F40: =IFERROR(INDEX(tbl_Collections[Outstanding Balance], ROW() - 34), 0) | G40: =IFERROR(INDEX(tbl_Collections[Status], ROW() - 34), "")
B41: =IFERROR(INDEX(tbl_Collections[Month], ROW() - 34), "") | C41: =IFERROR(INDEX(tbl_Collections[Member], ROW() - 34), "") | D41: =IFERROR(INDEX(tbl_Collections[Standard Contribution], ROW() - 34)+INDEX(tbl_Collections[Extra Contribution], ROW() - 34), 0) | E41: =IFERROR(INDEX(tbl_Collections[Total Paid], ROW() - 34), 0) | F41: =IFERROR(INDEX(tbl_Collections[Outstanding Balance], ROW() - 34), 0) | G41: =IFERROR(INDEX(tbl_Collections[Status], ROW() - 34), "")
B42: =IFERROR(INDEX(tbl_Collections[Month], ROW() - 34), "") | C42: =IFERROR(INDEX(tbl_Collections[Member], ROW() - 34), "") | D42: =IFERROR(INDEX(tbl_Collections[Standard Contribution], ROW() - 34)+INDEX(tbl_Collections[Extra Contribution], ROW() - 34), 0) | E42: =IFERROR(INDEX(tbl_Collections[Total Paid], ROW() - 34), 0) | F42: =IFERROR(INDEX(tbl_Collections[Outstanding Balance], ROW() - 34), 0) | G42: =IFERROR(INDEX(tbl_Collections[Status], ROW() - 34), "")
B43: =IFERROR(INDEX(tbl_Collections[Month], ROW() - 34), "") | C43: =IFERROR(INDEX(tbl_Collections[Member], ROW() - 34), "") | D43: =IFERROR(INDEX(tbl_Collections[Standard Contribution], ROW() - 34)+INDEX(tbl_Collections[Extra Contribution], ROW() - 34), 0) | E43: =IFERROR(INDEX(tbl_Collections[Total Paid], ROW() - 34), 0) | F43: =IFERROR(INDEX(tbl_Collections[Outstanding Balance], ROW() - 34), 0) | G43: =IFERROR(INDEX(tbl_Collections[Status], ROW() - 34), "")
B44: =IFERROR(INDEX(tbl_Collections[Month], ROW() - 34), "") | C44: =IFERROR(INDEX(tbl_Collections[Member], ROW() - 34), "") | D44: =IFERROR(INDEX(tbl_Collections[Standard Contribution], ROW() - 34)+INDEX(tbl_Collections[Extra Contribution], ROW() - 34), 0) | E44: =IFERROR(INDEX(tbl_Collections[Total Paid], ROW() - 34), 0) | F44: =IFERROR(INDEX(tbl_Collections[Outstanding Balance], ROW() - 34), 0) | G44: =IFERROR(INDEX(tbl_Collections[Status], ROW() - 34), "")
B45: =IFERROR(INDEX(tbl_Collections[Month], ROW() - 34), "") | C45: =IFERROR(INDEX(tbl_Collections[Member], ROW() - 34), "") | D45: =IFERROR(INDEX(tbl_Collections[Standard Contribution], ROW() - 34)+INDEX(tbl_Collections[Extra Contribution], ROW() - 34), 0) | E45: =IFERROR(INDEX(tbl_Collections[Total Paid], ROW() - 34), 0) | F45: =IFERROR(INDEX(tbl_Collections[Outstanding Balance], ROW() - 34), 0) | G45: =IFERROR(INDEX(tbl_Collections[Status], ROW() - 34), "")
B46: =IFERROR(INDEX(tbl_Collections[Month], ROW() - 34), "") | C46: =IFERROR(INDEX(tbl_Collections[Member], ROW() - 34), "") | D46: =IFERROR(INDEX(tbl_Collections[Standard Contribution], ROW() - 34)+INDEX(tbl_Collections[Extra Contribution], ROW() - 34), 0) | E46: =IFERROR(INDEX(tbl_Collections[Total Paid], ROW() - 34), 0) | F46: =IFERROR(INDEX(tbl_Collections[Outstanding Balance], ROW() - 34), 0) | G46: =IFERROR(INDEX(tbl_Collections[Status], ROW() - 34), "")
B48: 4. YEARLY PERFORMANCE SUMMARY REPORT
B49: Month | C49: Expected Collection | D49: Actual Collection | E49: Total Expenses | F49: Net Diff (Surplus/Def) | G49: Carry Forward
B50: =IFERROR(INDEX(tbl_MonthlySummary[Month], ROW() - 49), "") | C50: =IFERROR(INDEX(tbl_MonthlySummary[Expected Collection], ROW() - 49), 0) | D50: =IFERROR(INDEX(tbl_MonthlySummary[Actual Collection], ROW() - 49), 0) | E50: =IFERROR(INDEX(tbl_MonthlySummary[Total Expenses], ROW() - 49), 0) | F50: =IFERROR(INDEX(tbl_MonthlySummary[Surplus], ROW() - 49)-INDEX(tbl_MonthlySummary[Deficit], ROW() - 49), 0) | G50: =IFERROR(INDEX(tbl_MonthlySummary[Carry Forward], ROW() - 49), 0)
B51: =IFERROR(INDEX(tbl_MonthlySummary[Month], ROW() - 49), "") | C51: =IFERROR(INDEX(tbl_MonthlySummary[Expected Collection], ROW() - 49), 0) | D51: =IFERROR(INDEX(tbl_MonthlySummary[Actual Collection], ROW() - 49), 0) | E51: =IFERROR(INDEX(tbl_MonthlySummary[Total Expenses], ROW() - 49), 0) | F51: =IFERROR(INDEX(tbl_MonthlySummary[Surplus], ROW() - 49)-INDEX(tbl_MonthlySummary[Deficit], ROW() - 49), 0) | G51: =IFERROR(INDEX(tbl_MonthlySummary[Carry Forward], ROW() - 49), 0)
B52: =IFERROR(INDEX(tbl_MonthlySummary[Month], ROW() - 49), "") | C52: =IFERROR(INDEX(tbl_MonthlySummary[Expected Collection], ROW() - 49), 0) | D52: =IFERROR(INDEX(tbl_MonthlySummary[Actual Collection], ROW() - 49), 0) | E52: =IFERROR(INDEX(tbl_MonthlySummary[Total Expenses], ROW() - 49), 0) | F52: =IFERROR(INDEX(tbl_MonthlySummary[Surplus], ROW() - 49)-INDEX(tbl_MonthlySummary[Deficit], ROW() - 49), 0) | G52: =IFERROR(INDEX(tbl_MonthlySummary[Carry Forward], ROW() - 49), 0)
B53: =IFERROR(INDEX(tbl_MonthlySummary[Month], ROW() - 49), "") | C53: =IFERROR(INDEX(tbl_MonthlySummary[Expected Collection], ROW() - 49), 0) | D53: =IFERROR(INDEX(tbl_MonthlySummary[Actual Collection], ROW() - 49), 0) | E53: =IFERROR(INDEX(tbl_MonthlySummary[Total Expenses], ROW() - 49), 0) | F53: =IFERROR(INDEX(tbl_MonthlySummary[Surplus], ROW() - 49)-INDEX(tbl_MonthlySummary[Deficit], ROW() - 49), 0) | G53: =IFERROR(INDEX(tbl_MonthlySummary[Carry Forward], ROW() - 49), 0)
B54: =IFERROR(INDEX(tbl_MonthlySummary[Month], ROW() - 49), "") | C54: =IFERROR(INDEX(tbl_MonthlySummary[Expected Collection], ROW() - 49), 0) | D54: =IFERROR(INDEX(tbl_MonthlySummary[Actual Collection], ROW() - 49), 0) | E54: =IFERROR(INDEX(tbl_MonthlySummary[Total Expenses], ROW() - 49), 0) | F54: =IFERROR(INDEX(tbl_MonthlySummary[Surplus], ROW() - 49)-INDEX(tbl_MonthlySummary[Deficit], ROW() - 49), 0) | G54: =IFERROR(INDEX(tbl_MonthlySummary[Carry Forward], ROW() - 49), 0)
B55: =IFERROR(INDEX(tbl_MonthlySummary[Month], ROW() - 49), "") | C55: =IFERROR(INDEX(tbl_MonthlySummary[Expected Collection], ROW() - 49), 0) | D55: =IFERROR(INDEX(tbl_MonthlySummary[Actual Collection], ROW() - 49), 0) | E55: =IFERROR(INDEX(tbl_MonthlySummary[Total Expenses], ROW() - 49), 0) | F55: =IFERROR(INDEX(tbl_MonthlySummary[Surplus], ROW() - 49)-INDEX(tbl_MonthlySummary[Deficit], ROW() - 49), 0) | G55: =IFERROR(INDEX(tbl_MonthlySummary[Carry Forward], ROW() - 49), 0)
B56: =IFERROR(INDEX(tbl_MonthlySummary[Month], ROW() - 49), "") | C56: =IFERROR(INDEX(tbl_MonthlySummary[Expected Collection], ROW() - 49), 0) | D56: =IFERROR(INDEX(tbl_MonthlySummary[Actual Collection], ROW() - 49), 0) | E56: =IFERROR(INDEX(tbl_MonthlySummary[Total Expenses], ROW() - 49), 0) | F56: =IFERROR(INDEX(tbl_MonthlySummary[Surplus], ROW() - 49)-INDEX(tbl_MonthlySummary[Deficit], ROW() - 49), 0) | G56: =IFERROR(INDEX(tbl_MonthlySummary[Carry Forward], ROW() - 49), 0)
B57: =IFERROR(INDEX(tbl_MonthlySummary[Month], ROW() - 49), "") | C57: =IFERROR(INDEX(tbl_MonthlySummary[Expected Collection], ROW() - 49), 0) | D57: =IFERROR(INDEX(tbl_MonthlySummary[Actual Collection], ROW() - 49), 0) | E57: =IFERROR(INDEX(tbl_MonthlySummary[Total Expenses], ROW() - 49), 0) | F57: =IFERROR(INDEX(tbl_MonthlySummary[Surplus], ROW() - 49)-INDEX(tbl_MonthlySummary[Deficit], ROW() - 49), 0) | G57: =IFERROR(INDEX(tbl_MonthlySummary[Carry Forward], ROW() - 49), 0)
B58: =IFERROR(INDEX(tbl_MonthlySummary[Month], ROW() - 49), "") | C58: =IFERROR(INDEX(tbl_MonthlySummary[Expected Collection], ROW() - 49), 0) | D58: =IFERROR(INDEX(tbl_MonthlySummary[Actual Collection], ROW() - 49), 0) | E58: =IFERROR(INDEX(tbl_MonthlySummary[Total Expenses], ROW() - 49), 0) | F58: =IFERROR(INDEX(tbl_MonthlySummary[Surplus], ROW() - 49)-INDEX(tbl_MonthlySummary[Deficit], ROW() - 49), 0) | G58: =IFERROR(INDEX(tbl_MonthlySummary[Carry Forward], ROW() - 49), 0)
B59: =IFERROR(INDEX(tbl_MonthlySummary[Month], ROW() - 49), "") | C59: =IFERROR(INDEX(tbl_MonthlySummary[Expected Collection], ROW() - 49), 0) | D59: =IFERROR(INDEX(tbl_MonthlySummary[Actual Collection], ROW() - 49), 0) | E59: =IFERROR(INDEX(tbl_MonthlySummary[Total Expenses], ROW() - 49), 0) | F59: =IFERROR(INDEX(tbl_MonthlySummary[Surplus], ROW() - 49)-INDEX(tbl_MonthlySummary[Deficit], ROW() - 49), 0) | G59: =IFERROR(INDEX(tbl_MonthlySummary[Carry Forward], ROW() - 49), 0)
B60: =IFERROR(INDEX(tbl_MonthlySummary[Month], ROW() - 49), "") | C60: =IFERROR(INDEX(tbl_MonthlySummary[Expected Collection], ROW() - 49), 0) | D60: =IFERROR(INDEX(tbl_MonthlySummary[Actual Collection], ROW() - 49), 0) | E60: =IFERROR(INDEX(tbl_MonthlySummary[Total Expenses], ROW() - 49), 0) | F60: =IFERROR(INDEX(tbl_MonthlySummary[Surplus], ROW() - 49)-INDEX(tbl_MonthlySummary[Deficit], ROW() - 49), 0) | G60: =IFERROR(INDEX(tbl_MonthlySummary[Carry Forward], ROW() - 49), 0)
B61: =IFERROR(INDEX(tbl_MonthlySummary[Month], ROW() - 49), "") | C61: =IFERROR(INDEX(tbl_MonthlySummary[Expected Collection], ROW() - 49), 0) | D61: =IFERROR(INDEX(tbl_MonthlySummary[Actual Collection], ROW() - 49), 0) | E61: =IFERROR(INDEX(tbl_MonthlySummary[Total Expenses], ROW() - 49), 0) | F61: =IFERROR(INDEX(tbl_MonthlySummary[Surplus], ROW() - 49)-INDEX(tbl_MonthlySummary[Deficit], ROW() - 49), 0) | G61: =IFERROR(INDEX(tbl_MonthlySummary[Carry Forward], ROW() - 49), 0)
B63: 5. MEMBER STATEMENT REPORT
B64: Month | C64: Member Name | D64: Rent Paid | E64: Utility Paid | F64: Total Paid | G64: Payment Date
B65: =IFERROR(INDEX(tbl_Collections[Month], ROW() - 64), "") | C65: =IFERROR(INDEX(tbl_Collections[Member], ROW() - 64), "") | D65: =IFERROR(INDEX(tbl_Collections[Partial Payment], ROW() - 64), 0) | E65: =IFERROR(INDEX(tbl_Collections[Extra Contribution], ROW() - 64), 0) | F65: =IFERROR(INDEX(tbl_Collections[Total Paid], ROW() - 64), 0) | G65: =IFERROR(INDEX(tbl_Collections[Payment Date], ROW() - 64), "")
B66: =IFERROR(INDEX(tbl_Collections[Month], ROW() - 64), "") | C66: =IFERROR(INDEX(tbl_Collections[Member], ROW() - 64), "") | D66: =IFERROR(INDEX(tbl_Collections[Partial Payment], ROW() - 64), 0) | E66: =IFERROR(INDEX(tbl_Collections[Extra Contribution], ROW() - 64), 0) | F66: =IFERROR(INDEX(tbl_Collections[Total Paid], ROW() - 64), 0) | G66: =IFERROR(INDEX(tbl_Collections[Payment Date], ROW() - 64), "")
B67: =IFERROR(INDEX(tbl_Collections[Month], ROW() - 64), "") | C67: =IFERROR(INDEX(tbl_Collections[Member], ROW() - 64), "") | D67: =IFERROR(INDEX(tbl_Collections[Partial Payment], ROW() - 64), 0) | E67: =IFERROR(INDEX(tbl_Collections[Extra Contribution], ROW() - 64), 0) | F67: =IFERROR(INDEX(tbl_Collections[Total Paid], ROW() - 64), 0) | G67: =IFERROR(INDEX(tbl_Collections[Payment Date], ROW() - 64), "")
B68: =IFERROR(INDEX(tbl_Collections[Month], ROW() - 64), "") | C68: =IFERROR(INDEX(tbl_Collections[Member], ROW() - 64), "") | D68: =IFERROR(INDEX(tbl_Collections[Partial Payment], ROW() - 64), 0) | E68: =IFERROR(INDEX(tbl_Collections[Extra Contribution], ROW() - 64), 0) | F68: =IFERROR(INDEX(tbl_Collections[Total Paid], ROW() - 64), 0) | G68: =IFERROR(INDEX(tbl_Collections[Payment Date], ROW() - 64), "")
B69: =IFERROR(INDEX(tbl_Collections[Month], ROW() - 64), "") | C69: =IFERROR(INDEX(tbl_Collections[Member], ROW() - 64), "") | D69: =IFERROR(INDEX(tbl_Collections[Partial Payment], ROW() - 64), 0) | E69: =IFERROR(INDEX(tbl_Collections[Extra Contribution], ROW() - 64), 0) | F69: =IFERROR(INDEX(tbl_Collections[Total Paid], ROW() - 64), 0) | G69: =IFERROR(INDEX(tbl_Collections[Payment Date], ROW() - 64), "")
B70: =IFERROR(INDEX(tbl_Collections[Month], ROW() - 64), "") | C70: =IFERROR(INDEX(tbl_Collections[Member], ROW() - 64), "") | D70: =IFERROR(INDEX(tbl_Collections[Partial Payment], ROW() - 64), 0) | E70: =IFERROR(INDEX(tbl_Collections[Extra Contribution], ROW() - 64), 0) | F70: =IFERROR(INDEX(tbl_Collections[Total Paid], ROW() - 64), 0) | G70: =IFERROR(INDEX(tbl_Collections[Payment Date], ROW() - 64), "")
B71: =IFERROR(INDEX(tbl_Collections[Month], ROW() - 64), "") | C71: =IFERROR(INDEX(tbl_Collections[Member], ROW() - 64), "") | D71: =IFERROR(INDEX(tbl_Collections[Partial Payment], ROW() - 64), 0) | E71: =IFERROR(INDEX(tbl_Collections[Extra Contribution], ROW() - 64), 0) | F71: =IFERROR(INDEX(tbl_Collections[Total Paid], ROW() - 64), 0) | G71: =IFERROR(INDEX(tbl_Collections[Payment Date], ROW() - 64), "")
B72: =IFERROR(INDEX(tbl_Collections[Month], ROW() - 64), "") | C72: =IFERROR(INDEX(tbl_Collections[Member], ROW() - 64), "") | D72: =IFERROR(INDEX(tbl_Collections[Partial Payment], ROW() - 64), 0) | E72: =IFERROR(INDEX(tbl_Collections[Extra Contribution], ROW() - 64), 0) | F72: =IFERROR(INDEX(tbl_Collections[Total Paid], ROW() - 64), 0) | G72: =IFERROR(INDEX(tbl_Collections[Payment Date], ROW() - 64), "")
B73: =IFERROR(INDEX(tbl_Collections[Month], ROW() - 64), "") | C73: =IFERROR(INDEX(tbl_Collections[Member], ROW() - 64), "") | D73: =IFERROR(INDEX(tbl_Collections[Partial Payment], ROW() - 64), 0) | E73: =IFERROR(INDEX(tbl_Collections[Extra Contribution], ROW() - 64), 0) | F73: =IFERROR(INDEX(tbl_Collections[Total Paid], ROW() - 64), 0) | G73: =IFERROR(INDEX(tbl_Collections[Payment Date], ROW() - 64), "")
B74: =IFERROR(INDEX(tbl_Collections[Month], ROW() - 64), "") | C74: =IFERROR(INDEX(tbl_Collections[Member], ROW() - 64), "") | D74: =IFERROR(INDEX(tbl_Collections[Partial Payment], ROW() - 64), 0) | E74: =IFERROR(INDEX(tbl_Collections[Extra Contribution], ROW() - 64), 0) | F74: =IFERROR(INDEX(tbl_Collections[Total Paid], ROW() - 64), 0) | G74: =IFERROR(INDEX(tbl_Collections[Payment Date], ROW() - 64), "")
B75: =IFERROR(INDEX(tbl_Collections[Month], ROW() - 64), "") | C75: =IFERROR(INDEX(tbl_Collections[Member], ROW() - 64), "") | D75: =IFERROR(INDEX(tbl_Collections[Partial Payment], ROW() - 64), 0) | E75: =IFERROR(INDEX(tbl_Collections[Extra Contribution], ROW() - 64), 0) | F75: =IFERROR(INDEX(tbl_Collections[Total Paid], ROW() - 64), 0) | G75: =IFERROR(INDEX(tbl_Collections[Payment Date], ROW() - 64), "")
B76: =IFERROR(INDEX(tbl_Collections[Month], ROW() - 64), "") | C76: =IFERROR(INDEX(tbl_Collections[Member], ROW() - 64), "") | D76: =IFERROR(INDEX(tbl_Collections[Partial Payment], ROW() - 64), 0) | E76: =IFERROR(INDEX(tbl_Collections[Extra Contribution], ROW() - 64), 0) | F76: =IFERROR(INDEX(tbl_Collections[Total Paid], ROW() - 64), 0) | G76: =IFERROR(INDEX(tbl_Collections[Payment Date], ROW() - 64), "")
B78: 6. MISCELLANEOUS EXPENSE MASTER LOG REPORT
B79: Expense ID | C79: Date | D79: Category | E79: Description | F79: Amount | G79: Paid To
B80: =IFERROR(INDEX(tbl_ExpenseHistory[Expense ID], ROW() - 79), "") | C80: =IFERROR(INDEX(tbl_ExpenseHistory[Date], ROW() - 79), "") | D80: =IFERROR(INDEX(tbl_ExpenseHistory[Category], ROW() - 79), "") | E80: =IFERROR(INDEX(tbl_ExpenseHistory[Description], ROW() - 79), "") | F80: =IFERROR(INDEX(tbl_ExpenseHistory[Amount (LKR)], ROW() - 79), 0) | G80: =IFERROR(INDEX(tbl_ExpenseHistory[Paid To], ROW() - 79), "")
B81: =IFERROR(INDEX(tbl_ExpenseHistory[Expense ID], ROW() - 79), "") | C81: =IFERROR(INDEX(tbl_ExpenseHistory[Date], ROW() - 79), "") | D81: =IFERROR(INDEX(tbl_ExpenseHistory[Category], ROW() - 79), "") | E81: =IFERROR(INDEX(tbl_ExpenseHistory[Description], ROW() - 79), "") | F81: =IFERROR(INDEX(tbl_ExpenseHistory[Amount (LKR)], ROW() - 79), 0) | G81: =IFERROR(INDEX(tbl_ExpenseHistory[Paid To], ROW() - 79), "")
B82: =IFERROR(INDEX(tbl_ExpenseHistory[Expense ID], ROW() - 79), "") | C82: =IFERROR(INDEX(tbl_ExpenseHistory[Date], ROW() - 79), "") | D82: =IFERROR(INDEX(tbl_ExpenseHistory[Category], ROW() - 79), "") | E82: =IFERROR(INDEX(tbl_ExpenseHistory[Description], ROW() - 79), "") | F82: =IFERROR(INDEX(tbl_ExpenseHistory[Amount (LKR)], ROW() - 79), 0) | G82: =IFERROR(INDEX(tbl_ExpenseHistory[Paid To], ROW() - 79), "")
B83: =IFERROR(INDEX(tbl_ExpenseHistory[Expense ID], ROW() - 79), "") | C83: =IFERROR(INDEX(tbl_ExpenseHistory[Date], ROW() - 79), "") | D83: =IFERROR(INDEX(tbl_ExpenseHistory[Category], ROW() - 79), "") | E83: =IFERROR(INDEX(tbl_ExpenseHistory[Description], ROW() - 79), "") | F83: =IFERROR(INDEX(tbl_ExpenseHistory[Amount (LKR)], ROW() - 79), 0) | G83: =IFERROR(INDEX(tbl_ExpenseHistory[Paid To], ROW() - 79), "")
B84: =IFERROR(INDEX(tbl_ExpenseHistory[Expense ID], ROW() - 79), "") | C84: =IFERROR(INDEX(tbl_ExpenseHistory[Date], ROW() - 79), "") | D84: =IFERROR(INDEX(tbl_ExpenseHistory[Category], ROW() - 79), "") | E84: =IFERROR(INDEX(tbl_ExpenseHistory[Description], ROW() - 79), "") | F84: =IFERROR(INDEX(tbl_ExpenseHistory[Amount (LKR)], ROW() - 79), 0) | G84: =IFERROR(INDEX(tbl_ExpenseHistory[Paid To], ROW() - 79), "")
B85: =IFERROR(INDEX(tbl_ExpenseHistory[Expense ID], ROW() - 79), "") | C85: =IFERROR(INDEX(tbl_ExpenseHistory[Date], ROW() - 79), "") | D85: =IFERROR(INDEX(tbl_ExpenseHistory[Category], ROW() - 79), "") | E85: =IFERROR(INDEX(tbl_ExpenseHistory[Description], ROW() - 79), "") | F85: =IFERROR(INDEX(tbl_ExpenseHistory[Amount (LKR)], ROW() - 79), 0) | G85: =IFERROR(INDEX(tbl_ExpenseHistory[Paid To], ROW() - 79), "")
B86: =IFERROR(INDEX(tbl_ExpenseHistory[Expense ID], ROW() - 79), "") | C86: =IFERROR(INDEX(tbl_ExpenseHistory[Date], ROW() - 79), "") | D86: =IFERROR(INDEX(tbl_ExpenseHistory[Category], ROW() - 79), "") | E86: =IFERROR(INDEX(tbl_ExpenseHistory[Description], ROW() - 79), "") | F86: =IFERROR(INDEX(tbl_ExpenseHistory[Amount (LKR)], ROW() - 79), 0) | G86: =IFERROR(INDEX(tbl_ExpenseHistory[Paid To], ROW() - 79), "")
B87: =IFERROR(INDEX(tbl_ExpenseHistory[Expense ID], ROW() - 79), "") | C87: =IFERROR(INDEX(tbl_ExpenseHistory[Date], ROW() - 79), "") | D87: =IFERROR(INDEX(tbl_ExpenseHistory[Category], ROW() - 79), "") | E87: =IFERROR(INDEX(tbl_ExpenseHistory[Description], ROW() - 79), "") | F87: =IFERROR(INDEX(tbl_ExpenseHistory[Amount (LKR)], ROW() - 79), 0) | G87: =IFERROR(INDEX(tbl_ExpenseHistory[Paid To], ROW() - 79), "")
B88: =IFERROR(INDEX(tbl_ExpenseHistory[Expense ID], ROW() - 79), "") | C88: =IFERROR(INDEX(tbl_ExpenseHistory[Date], ROW() - 79), "") | D88: =IFERROR(INDEX(tbl_ExpenseHistory[Category], ROW() - 79), "") | E88: =IFERROR(INDEX(tbl_ExpenseHistory[Description], ROW() - 79), "") | F88: =IFERROR(INDEX(tbl_ExpenseHistory[Amount (LKR)], ROW() - 79), 0) | G88: =IFERROR(INDEX(tbl_ExpenseHistory[Paid To], ROW() - 79), "")
B89: =IFERROR(INDEX(tbl_ExpenseHistory[Expense ID], ROW() - 79), "") | C89: =IFERROR(INDEX(tbl_ExpenseHistory[Date], ROW() - 79), "") | D89: =IFERROR(INDEX(tbl_ExpenseHistory[Category], ROW() - 79), "") | E89: =IFERROR(INDEX(tbl_ExpenseHistory[Description], ROW() - 79), "") | F89: =IFERROR(INDEX(tbl_ExpenseHistory[Amount (LKR)], ROW() - 79), 0) | G89: =IFERROR(INDEX(tbl_ExpenseHistory[Paid To], ROW() - 79), "")
B90: =IFERROR(INDEX(tbl_ExpenseHistory[Expense ID], ROW() - 79), "") | C90: =IFERROR(INDEX(tbl_ExpenseHistory[Date], ROW() - 79), "") | D90: =IFERROR(INDEX(tbl_ExpenseHistory[Category], ROW() - 79), "") | E90: =IFERROR(INDEX(tbl_ExpenseHistory[Description], ROW() - 79), "") | F90: =IFERROR(INDEX(tbl_ExpenseHistory[Amount (LKR)], ROW() - 79), 0) | G90: =IFERROR(INDEX(tbl_ExpenseHistory[Paid To], ROW() - 79), "")

Sheet Settings
B1: SYSTEM VARIABLES & CONFIGURATION SETTINGS
B2: Define billing parameters, currency units, roommate slots, and business rules
B4: Setting_ID | C4: Parameter_Name | D4: Setting_Value | E4: Description
B5: SET001 | C5: Currency | D5: LKR | E5: Base currency unit for boarding payments
B6: SET002 | C6: Default Monthly Contribution | D6: 1000 | E6: Default monthly fee per roommate
B7: SET003 | C7: Financial Year | D7: 2026 | E7: Current financial operational year
B8: SET004 | C8: Start Month | D8: April | E8: Month marking the start of the financial year
B9: SET005 | C9: Maximum Members | D9: 8 | E9: Maximum capacity of active roommates
B10: SET006 | C10: Theme | D10: Blue & White | E10: Color palette and visual theme

Sheet Help
B1: BOARDING HOUSE UTILITY SYSTEM v2.0 - OPERATOR USER MANUAL
B3: 1. SYSTEM INITIALIZATION & REGISTRATION
B4: 1.1 Configuration Variables
C5: Navigate to the Settings tab to set the Default Monthly Contribution, Financial Year, and Currency (defaults to LKR). Values propagate workbook-wide.
B7: 1.2 Roommate Registry
C8: Add roommate profiles on the Members sheet. Enter their Full Name, Room Number, Phone, Status (Active/Inactive), and dates. Active status controls monthly splits.
B10: 2. OPERATIONS & DATA ENTRY WORKFLOW
B11: 2.1 Logging Collections
C12: Record monthly rents and extra payments in Monthly_Collections. The system auto-calculates totals and checks if payment dates occur after the 10th (Late status).
B14: 2.2 Recording Monthly Utility Bills
C15: Log Water, Electricity, WiFi, Gas, and Cleaning costs in Utility_Bills. Total expenses calculate dynamically and update Dashboard graphs.
B17: 2.3 Transactional Expense History
C18: Log miscellaneous costs (maintenance, repairs, supplies) in Expense_History. The Month column calculates automatically based on Date.
B19: 3. FINANCE DASHBOARDS & ANALYTICS
B20: 3.1 Core Dashboard
C21: Open the Dashboard sheet to view high-level collections, outstanding balances, unpaid utility bills count, and cash flows. 6 dynamic trend charts are plotted.
B23: 3.2 Performance Analytics
C24: Open the Analytics sheet to find Highest, Lowest, and Average Utility Bills, alongside an automated payment ledger comparison chart for each roommate.
B27: 4. PRINTING & DATA SECURITY
B28: 4.1 Exporting Reports to PDF
C29: Go to the Reports tab. It aggregates 6 printable reports (Collections, Utilities, Outstanding, Yearly Summary, Roommate Statement, and Expense Log). Ready to print to A4.
B31: 4.2 Cell Locks & Sheet Protection
C32: All workspaces are protected. Headers, KPI logic, charts, and formula columns are protected from accidental modifications. Only data entry cells are editable.
